[{"pr": 34.99, "sz": " M, L", "pp": 0.0, "sx": "U", "nm": "<a href=\"http://www.decathlon.pl/kask-mtb-st-50-id_8500051.html\">Kask na rower MTB ST 50 B'TWIN</a>", "dc": 13, "sc": "Odzie\u00c5\u00bc rowerowa", "or": "Nowa", "op": 39.99}, {"pr": 149.99, "sz": " 2XL", "pp": 149.99, "sx": "M", "nm": "<a href=\"http://www.decathlon.pl/ciepa-kurtka-pdeszczowa-900-id_8369479.html\">Ciep\u0142a Kurtka Przeciwdeszczowa Na Rower 900 M\u0119ska B'Twin</a>", "dc": 25, "sc": "Odzie\u00c5\u00bc rowerowa", "or": "Powr\u00f3t", "op": 199.99}, {"pr": 149.99, "sz": " 42", "pp": 149.99, "sx": "F", "nm": "<a href=\"http://www.decathlon.pl/ciepa-kurtka-pdeszczowa-900-id_8369480.html\">Ciep\u0142a Kurtka Przeciwdeszczowa Na Rower 900 Damska B'Twin</a>", "dc": 25, "sc": "Odzie\u00c5\u00bc rowerowa", "or": "Powr\u00f3t", "op": 199.99}, {"pr": 189.99, "sz": " 40, 41, 42, 43, 44, 45", "pp": 0.0, "sx": "M", "nm": "<a href=\"http://www.decathlon.pl/buty-riverbed-mskie-id_8388010.html\">Buty turystyczne niskie Riverbed Merrell m\u0119skie MERRELL</a>", "dc": 37, "sc": "Turystyka krajoznawcza", "or": "Nowa", "op": 299.99}, {"pr": 19.99, "sz": " S, XL, 2XL, 3XL", "pp": 19.99, "sx": "M", "nm": "<a href=\"http://www.decathlon.pl/sweter-nh150-mski-id_8396162.html\">Sweter turystyczny NH150 m\u0119ski QUECHUA</a>", "dc": 60, "sc": "Turystyka krajoznawcza", "or": "Powr\u00f3t", "op": 49.99}, {"pr": 7.99, "sz": " 2 LATA, 3 JAAR, 4 LATA, 5 ANS, 6 LAT", "pp": 0.0, "sx": "J", "nm": "<a href=\"http://www.decathlon.pl/spodenki-hike-100-dla-dzieci-id_8501846.html\">Spodenki turystyczne Hike 100 dla ch\u0142opc\u00f3w QUECHUA</a>", "dc": 73, "sc": "Turystyka g\u00c3\u00b3rska", "or": "Nowa", "op": 29.99}, {"pr": 9.99, "sz": " 8 LAT, 10 LAT, 12 LAT, 14 LAT", "pp": 0.0, "sx": "J", "nm": "<a href=\"http://www.decathlon.pl/koszulka-hike-500-dla-chopcow-id_8383254.html\">Koszulka turystyczna Hike 500 dla ch\u0142opc\u00f3w QUECHUA</a>", "dc": 60, "sc": "Turystyka g\u00c3\u00b3rska", "or": "Nowa", "op": 24.99}, {"pr": 19.99, "sz": " 2 LATA, 3 JAAR, 5 ANS", "pp": 0.0, "sx": "J", "nm": "<a href=\"http://www.decathlon.pl/spodnie-hike-500-dla-dzieci-id_8383258.html\">Spodnie turystyczne Hike 500 dla ch\u0142opc\u00f3w QUECHUA</a>", "dc": 60, "sc": "Turystyka g\u00c3\u00b3rska", "or": "Nowa", "op": 49.99}, {"pr": 9.99, "sz": " 3 - 4 LATA, 4 - 6 ANS", "pp": 0.0, "sx": "J", "nm": "<a href=\"http://www.decathlon.pl/kapelusz-hike-500-dla-dzieci-id_8383637.html\">Kapelusz turystyczny Hike 500 dla dziewczynek QUECHUA</a>", "dc": 60, "sc": "Turystyka g\u00c3\u00b3rska", "or": "Nowa", "op": 24.99}, {"pr": 69.99, "sz": " 8 LAT, 10 LAT, 14 LAT", "pp": 0.0, "sx": "J", "nm": "<a href=\"http://www.decathlon.pl/kurtka-hike-900-dziewczynki-id_8493204.html\">Kurtka turystyczna Hike 900 dla dziewczynek QUECHUA</a>", "dc": 53, "sc": "Turystyka g\u00c3\u00b3rska", "or": "Nowa", "op": 149.99}, {"pr": 14.99, "sz": " S, L, XL, 2XL, 3XL", "pp": 0.0, "sx": "M", "nm": "<a href=\"http://www.decathlon.pl/polar-turystyczny-forclaz-50-mski-id_8219987.html\">Polar turystyczny Forclaz 50 m\u0119ski QUECHUA</a>", "dc": 50, "sc": "Turystyka g\u00c3\u00b3rska", "or": "Nowa", "op": 29.99}, {"pr": 24.99, "sz": " 8 LAT, 10 LAT, 12 LAT, 14 LAT", "pp": 0.0, "sx": "J", "nm": "<a href=\"http://www.decathlon.pl/spodnie-hike-500-dla-dzieci-id_8383261.html\">Spodnie turystyczne Hike 500 dla ch\u0142opc\u00f3w QUECHUA</a>", "dc": 50, "sc": "Turystyka g\u00c3\u00b3rska", "or": "Nowa", "op": 49.99}, {"pr": 19.99, "sz": " 8 LAT, 10 LAT, 12 LAT, 14 LAT", "pp": 0.0, "sx": "J", "nm": "<a href=\"http://www.decathlon.pl/koszulka-hike-900-dla-dzieci-id_8386127.html\">Koszulka turystyczna Hike 900 dla ch\u0142opc\u00f3w QUECHUA</a>", "dc": 50, "sc": "Turystyka g\u00c3\u00b3rska", "or": "Nowa", "op": 39.99}, {"pr": 19.99, "sz": " 8 LAT, 10 LAT, 12 LAT, 14 LAT", "pp": 0.0, "sx": "J", "nm": "<a href=\"http://www.decathlon.pl/spodenki-hike-500-dla-dzieci-id_8493117.html\">Spodenki turystyczne Hike 500 dla dziewczynek QUECHUA</a>", "dc": 50, "sc": "Turystyka g\u00c3\u00b3rska", "or": "Nowa", "op": 39.99}, {"pr": 19.99, "sz": " 8 LAT, 10 LAT, 12 LAT, 14 LAT", "pp": 0.0, "sx": "J", "nm": "<a href=\"http://www.decathlon.pl/spodenki-hike-500-dla-dzieci-id_8493131.html\">Spodenki turystyczne Hike 500 dla ch\u0142opc\u00f3w QUECHUA</a>", "dc": 50, "sc": "Turystyka g\u00c3\u00b3rska", "or": "Nowa", "op": 39.99}, {"pr": 29.99, "sz": " 4 LATA, 6 LAT", "pp": 0.0, "sx": "J", "nm": "<a href=\"http://www.decathlon.pl/kurtka-hike-500-dla-chopcow-id_8493199.html\">Kurtka turystyczna Hike 500 dla ch\u0142opc\u00f3w QUECHUA</a>", "dc": 50, "sc": "Turystyka g\u00c3\u00b3rska", "or": "Nowa", "op": 59.99}, {"pr": 19.99, "sz": " 2 LATA, 3 JAAR, 4 LATA, 5 ANS, 6 LAT", "pp": 0.0, "sx": "J", "nm": "<a href=\"http://www.decathlon.pl/spodnico-spodenki-hike-100-id_8383144.html\">Sp\u00f3dnico-spodenki turystyczne Hike 100 dla dziewczynek QUECHUA</a>", "dc": 33, "sc": "Turystyka g\u00c3\u00b3rska", "or": "Nowa", "op": 29.99}, {"pr": 54.99, "sz": " 10 LAT", "pp": 0.0, "sx": "J", "nm": "<a href=\"http://www.decathlon.pl/kurtka-hike-500-dla-chopcow-id_8386109.html\">Kurtka turystyczna Hike 500 dla ch\u0142opc\u00f3w QUECHUA</a>", "dc": 31, "sc": "Turystyka g\u00c3\u00b3rska", "or": "Nowa", "op": 79.99}, {"pr": 54.99, "sz": " 42, 46", "pp": 0.0, "sx": "M", "nm": "<a href=\"http://www.decathlon.pl/spodenki-mh500-mskie-nb-id_8493713.html\">Spodenki turystyczne MH500 m\u0119skie QUECHUA</a>", "dc": 31, "sc": "Turystyka g\u00c3\u00b3rska", "or": "Nowa", "op": 79.99}, {"pr": 69.99, "sz": " 28/29, 30/31, 32/33, 34/35, 36/37, 38/39", "pp": 0.0, "sx": "J", "nm": "<a href=\"http://www.decathlon.pl/sanday-nh900-dla-dzieci-id_8357658.html\">Sanda\u0142y turystyczne NH900 dla dzieci QUECHUA</a>", "dc": 30, "sc": "Turystyka g\u00c3\u00b3rska", "or": "Nowa", "op": 99.99}, {"pr": 49.99, "sz": " 8 LAT, 10 LAT, 12 LAT, 14 LAT", "pp": 0.0, "sx": "J", "nm": "<a href=\"http://www.decathlon.pl/spodnie-hike-500-dla-dzieci-id_8493145.html\">Spodnie turystyczne Hike 500 dla dziewczynek QUECHUA</a>", "dc": 29, "sc": "Turystyka g\u00c3\u00b3rska", "or": "Nowa", "op": 69.99}, {"pr": 39.99, "sz": " S, M", "pp": 0.0, "sx": "M", "nm": "<a href=\"http://www.decathlon.pl/polar-turystyczny-forclaz-200-mski-id_8397186.html\">Kurtka polarowa turystyczna Forclaz 200 m\u0119ska QUECHUA</a>", "dc": 20, "sc": "Turystyka g\u00c3\u00b3rska", "or": "Nowa", "op": 49.99}, {"pr": 16.99, "sz": " 3 JAAR, 5 ANS, 6 LAT", "pp": 0.0, "sx": "J", "nm": "<a href=\"http://www.decathlon.pl/koszulka-hike-500-dla-dzieci-id_8383433.html\">Koszulka turystyczna Hike 500 dla ch\u0142opc\u00f3w QUECHUA</a>", "dc": 15, "sc": "Turystyka g\u00c3\u00b3rska", "or": "Nowa", "op": 19.99}, {"pr": 29.99, "sz": " 10 LAT, 12 LAT, 14 LAT", "pp": 39.99, "sx": "J", "nm": "<a href=\"http://www.decathlon.pl/kamizelka-hike-500-dla-dzieci-id_8398188.html\">Kurtka turystyczna Hike 500 dla ch\u0142opc\u00f3w QUECHUA</a>", "dc": 50, "sc": "Turystyka g\u00c3\u00b3rska", "or": "Ni\u017csza cena z 39.99", "op": 59.99}, {"pr": 14.99, "sz": " 2XL", "pp": 24.99, "sx": "F", "nm": "<a href=\"http://www.decathlon.pl/polar-forclaz-50-damski-id_8397204.html\">Polar turystyczny Forclaz 50 damski  QUECHUA</a>", "dc": 50, "sc": "Turystyka g\u00c3\u00b3rska", "or": "Ni\u017csza cena z 24.99", "op": 29.99}, {"pr": 34.99, "sz": " 2XL", "pp": 34.99, "sx": "F", "nm": "<a href=\"http://www.decathlon.pl/polar-turystyczny-forclaz-200-damski-id_8369596.html\">Kurtka turystyczna polarowa Forclaz 200 damska  QUECHUA</a>", "dc": 30, "sc": "Turystyka g\u00c3\u00b3rska", "or": "Powr\u00f3t", "op": 49.99}, {"pr": 139.99, "sz": " S, M, L", "pp": 0.0, "sx": "F", "nm": "<a href=\"http://www.decathlon.pl/kurtka-sh500-active-warm--id_8370087.html\">Kurtka turystyczna SH500 Active Warm damska QUECHUA</a>", "dc": 62, "sc": "W\u00c4\u0099dr\u00c3\u00b3wki po \u00c5\u009bniegu w g\u00c3\u00b3rach", "or": "Nowa", "op": 369.99}, {"pr": 99.99, "sz": " L, XL, 2XL, 3XL", "pp": 0.0, "sx": "M", "nm": "<a href=\"http://www.decathlon.pl/polar-sh500-active-warm-mski-id_8397432.html\">Polar turystyczny SH500 active warm m\u0119ski QUECHUA</a>", "dc": 44, "sc": "W\u00c4\u0099dr\u00c3\u00b3wki po \u00c5\u009bniegu w g\u00c3\u00b3rach", "or": "Nowa", "op": 179.99}, {"pr": 89.99, "sz": " 2XL", "pp": 0.0, "sx": "F", "nm": "<a href=\"http://www.decathlon.pl/polar-turystyczny-damski-arpenaz-700-id_8286820.html\">Sweter turystyczny Snow Hiking 500 warm damski QUECHUA</a>", "dc": 40, "sc": "W\u00c4\u0099dr\u00c3\u00b3wki po \u00c5\u009bniegu w g\u00c3\u00b3rach", "or": "Nowa", "op": 149.99}, {"pr": 119.99, "sz": " XL / W37 L34", "pp": 0.0, "sx": "M", "nm": "<a href=\"http://www.decathlon.pl/spodnie-sh500-warm-mskie-id_8397774.html\">Spodnie turystyczne SH900 Warm m\u0119skie QUECHUA</a>", "dc": 40, "sc": "W\u00c4\u0099dr\u00c3\u00b3wki po \u00c5\u009bniegu w g\u00c3\u00b3rach", "or": "Nowa", "op": 199.99}, {"pr": 79.99, "sz": " M / W32 L31, M / W32 L33, L / W34 L32, XL / W37 L32", "pp": 0.0, "sx": "M", "nm": "<a href=\"http://www.decathlon.pl/spodnie-100-warm-mskie-id_8369741.html\">Spodnie turystyczne Snow Hiking 100 warm m\u0119skie QUECHUA</a>", "dc": 38, "sc": "W\u00c4\u0099dr\u00c3\u00b3wki po \u00c5\u009bniegu w g\u00c3\u00b3rach", "or": "Nowa", "op": 129.99}, {"pr": 199.99, "sz": " 40", "pp": 0.0, "sx": "M", "nm": "<a href=\"http://www.decathlon.pl/spodnie-500-active-warm-mskie-id_8317876.html\">Spodnie Snow Hiking 500 active warm m\u0119skie QUECHUA</a>", "dc": 33, "sc": "W\u00c4\u0099dr\u00c3\u00b3wki po \u00c5\u009bniegu w g\u00c3\u00b3rach", "or": "Nowa", "op": 299.99}, {"pr": 99.99, "sz": " M, L, XL, 2XL", "pp": 0.0, "sx": "F", "nm": "<a href=\"http://www.decathlon.pl/kurtka-sh-500-warm-damska-id_8398573.html\">Kurtka turystyczna SH 500 Warm damska QUECHUA</a>", "dc": 33, "sc": "W\u00c4\u0099dr\u00c3\u00b3wki po \u00c5\u009bniegu w g\u00c3\u00b3rach", "or": "Nowa", "op": 149.99}, {"pr": 89.99, "sz": " M, L", "pp": 0.0, "sx": "M", "nm": "<a href=\"http://www.decathlon.pl/polar-sh500-warm-mski-id_8369578.html\">Polar turystyczny SH500 warm m\u0119ski QUECHUA</a>", "dc": 31, "sc": "W\u00c4\u0099dr\u00c3\u00b3wki po \u00c5\u009bniegu w g\u00c3\u00b3rach", "or": "Nowa", "op": 129.99}, {"pr": 29.99, "sz": " 27/30, 31/34, 35/38", "pp": 0.0, "sx": "J", "nm": "<a href=\"http://www.decathlon.pl/ciepe-skarpety-turystyczne-forclaz-dzieci-id_8319692.html\">Buty turystyczne Snow Hiking 500 active warm dla dzieci QUECHUA</a>", "dc": 25, "sc": "W\u00c4\u0099dr\u00c3\u00b3wki po \u00c5\u009bniegu w g\u00c3\u00b3rach", "or": "Nowa", "op": 39.99}, {"pr": 54.99, "sz": " M, L", "pp": 0.0, "sx": "M", "nm": "<a href=\"http://www.decathlon.pl/koszulka-turystyczna-forclaz-500-warm-mska-id_8319420.html\">Koszulka d\u0142ugi r\u0119kaw SH500 active warm m\u0119ska QUECHUA</a>", "dc": 21, "sc": "W\u00c4\u0099dr\u00c3\u00b3wki po \u00c5\u009bniegu w g\u00c3\u00b3rach", "or": "Nowa", "op": 69.99}, {"pr": 59.99, "sz": " 2 LATA, 3 JAAR", "pp": 0.0, "sx": "J", "nm": "<a href=\"http://www.decathlon.pl/kurtka-turystyczna-hike-100-warm-dzieci-id_8370456.html\">Kurtka turystyczna Hike 100 dla dzieci QUECHUA</a>", "dc": 14, "sc": "W\u00c4\u0099dr\u00c3\u00b3wki po \u00c5\u009bniegu w g\u00c3\u00b3rach", "or": "Nowa", "op": 69.99}, {"pr": 89.99, "sz": " 47", "pp": 89.99, "sx": "M", "nm": "<a href=\"http://www.decathlon.pl/buty-500-warm-mskie-id_8367595.html\">Buty turystyczne Snow Hiking 500 warm m\u0119skie QUECHUA</a>", "dc": 36, "sc": "W\u00c4\u0099dr\u00c3\u00b3wki po \u00c5\u009bniegu w g\u00c3\u00b3rach", "or": "Powr\u00f3t", "op": 139.99}, {"pr": 29.99, "sz": " ", "pp": 0.0, "sx": "J", "nm": "<a href=\"http://www.decathlon.pl/okulary-mh-t-500-kat4-id_8394849.html\">Okulary przeciws\u0142oneczne turystyczne MH T500 dla dzieci 7 - 10 lat kat. 4 QUECHUA</a>", "dc": 40, "sc": "Akcesoria turystyczne", "or": "Nowa", "op": 49.99}, {"pr": 11.99, "sz": " ", "pp": 11.99, "sx": "U", "nm": "<a href=\"http://www.decathlon.pl/busola-c100-id_8360906.html\">Busola C100 GEONAUTE</a>", "dc": 40, "sc": "Akcesoria turystyczne", "or": "Powr\u00f3t", "op": 19.99}, {"pr": 29.99, "sz": " 56 CM, 58 CM, 60 CM", "pp": 0.0, "sx": "F", "nm": "<a href=\"http://www.decathlon.pl/kapelusz-trek-500-damski-id_8493571.html\">Kapelusz TREK 500 damski dwustronny FORCLAZ</a>", "dc": 25, "sc": "Czapki, kapelusze turystyczne", "or": "Nowa", "op": 39.99}, {"pr": 59.99, "sz": " S", "pp": 0.0, "sx": "M", "nm": "<a href=\"http://www.decathlon.pl/kurtka-x-light-mska-id_8397255.html\">Kurtka trekkingowa zimowa X-Light m\u0119ska QUECHUA</a>", "dc": 54, "sc": "Trekking g\u00c3\u00b3rski", "or": "Nowa", "op": 129.99}, {"pr": 89.99, "sz": " 38, 40, 44, 48, 50", "pp": 0.0, "sx": "M", "nm": "<a href=\"http://www.decathlon.pl/spodnie-travel-100-mskie-id_8382881.html\">Spodnie turystyczne m\u0119skie 2w1 Travel 100 m\u0119skie QUECHUA</a>", "dc": 40, "sc": "Backpacking", "or": "Nowa", "op": 149.99}, {"pr": 179.99, "sz": " 36, 37, 38, 39, 40, 41, 42", "pp": 0.0, "sx": "F", "nm": "<a href=\"http://www.decathlon.pl/sanday-turystyczne-kyra-vent-damskie-id_8359960.html\">SANDA\u0141Y TURYSTYCZNE DAMSKIE Kyra Vent COLUMBIA</a>", "dc": 28, "sc": "Backpacking", "or": "Nowa", "op": 249.99}, {"pr": 49.99, "sz": " S, M, XL, 2XL", "pp": 0.0, "sx": "M", "nm": "<a href=\"http://www.decathlon.pl/koszula-travel100-fresh-mska-id_8493326.html\">Koszula turystyczna kr\u00f3tki r\u0119kaw TRAVEL100 FRESH m\u0119ska QUECHUA</a>", "dc": 29, "sc": "Koszule i spodnie backpackingowe", "or": "Nowa", "op": 69.99}, {"pr": 49.99, "sz": " XS, S, M, L, XL, 2XL", "pp": 0.0, "sx": "F", "nm": "<a href=\"http://www.decathlon.pl/koszula-travel-100-damska-id_8493755.html\">Koszula z kr\u00f3tkim r\u0119kawem TRAVEL 100 damska QUECHUA</a>", "dc": 17, "sc": "Koszule i spodnie backpackingowe", "or": "Nowa", "op": 59.99}, {"pr": 24.99, "sz": " M", "pp": 0.0, "sx": "M", "nm": "<a href=\"http://www.decathlon.pl/spodenki-kardio-fst900-id_8491900.html\">Spodenki fitness kardio FST900 m\u0119skie DOMYOS</a>", "dc": 69, "sc": "Odzie\u00c5\u00bc Fitness Cardio", "or": "Nowa", "op": 79.99}, {"pr": 29.99, "sz": " S, M, L, XL, 2XL", "pp": 0.0, "sx": "M", "nm": "<a href=\"http://www.decathlon.pl/bluza-fitness-fsw500-id_8483940.html\">Bluza fitness kardio FSW500 m\u0119ska DOMYOS</a>", "dc": 63, "sc": "Odzie\u00c5\u00bc Fitness Cardio", "or": "Nowa", "op": 79.99}, {"pr": 24.99, "sz": " L, XL", "pp": 0.0, "sx": "M", "nm": "<a href=\"http://www.decathlon.pl/koszulka-cardio-fts-920-id_8485079.html\">Koszulka fitness kr\u00f3tki r\u0119kaw FTS920 m\u0119ska DOMYOS</a>", "dc": 58, "sc": "Odzie\u00c5\u00bc Fitness Cardio", "or": "Nowa", "op": 59.99}, {"pr": 34.99, "sz": " M", "pp": 0.0, "sx": "M", "nm": "<a href=\"http://www.decathlon.pl/spodenki-kardio-fst500-id_8491894.html\">Spodenki fitness cardio FST500 DOMYOS</a>", "dc": 42, "sc": "Odzie\u00c5\u00bc Fitness Cardio", "or": "Nowa", "op": 59.99}, {"pr": 34.99, "sz": " M, L, XL", "pp": 0.0, "sx": "M", "nm": "<a href=\"http://www.decathlon.pl/spodenki-kardio-fst500-id_8491895.html\">Spodenki fitness kardio FST500 m\u0119skie DOMYOS</a>", "dc": 42, "sc": "Odzie\u00c5\u00bc Fitness Cardio", "or": "Nowa", "op": 59.99}, {"pr": 19.99, "sz": " S", "pp": 0.0, "sx": "F", "nm": "<a href=\"http://www.decathlon.pl/stanik-fitness-kardio-100-id_8397037.html\">Stanik fitness CONFORT+ DOMYOS</a>", "dc": 33, "sc": "Odzie\u00c5\u00bc Fitness Cardio", "or": "Nowa", "op": 29.99}, {"pr": 19.99, "sz": " M", "pp": 0.0, "sx": "M", "nm": "<a href=\"http://www.decathlon.pl/spodenki-kardio-fst120-id_8484478.html\">Spodenki fitness kardio FST120 m\u0119skie DOMYOS</a>", "dc": 33, "sc": "Odzie\u00c5\u00bc Fitness Cardio", "or": "Nowa", "op": 29.99}, {"pr": 39.99, "sz": " XS, S, L", "pp": 0.0, "sx": "F", "nm": "<a href=\"http://www.decathlon.pl/stanik-fitness-cardio-500-id_8484735.html\">Stanik fitness kardio 500 DOMYOS</a>", "dc": 33, "sc": "Odzie\u00c5\u00bc Fitness Cardio", "or": "Nowa", "op": 59.99}, {"pr": 54.99, "sz": " L", "pp": 0.0, "sx": "M", "nm": "<a href=\"http://www.decathlon.pl/koszulka-puma-e2-id_8406527.html\">Koszulka kr\u00f3tki r\u0119kaw fitness kardio E2 m\u0119ska PUMA</a>", "dc": 31, "sc": "Odzie\u00c5\u00bc Fitness Cardio", "or": "Nowa", "op": 79.99}, {"pr": 44.99, "sz": " 42", "pp": 0.0, "sx": "F", "nm": "<a href=\"http://www.decathlon.pl/koszulka-fitness-cardio-500-id_8484638.html\">Top fitness kardio 500 damski DOMYOS</a>", "dc": 31, "sc": "Odzie\u00c5\u00bc Fitness Cardio", "or": "Nowa", "op": 64.99}, {"pr": 54.99, "sz": " S", "pp": 0.0, "sx": "F", "nm": "<a href=\"http://www.decathlon.pl/stanik-fitness-kardio-900-id_8484729.html\">Stanik fitness kardio 900 DOMYOS</a>", "dc": 31, "sc": "Odzie\u00c5\u00bc Fitness Cardio", "or": "Nowa", "op": 79.99}, {"pr": 69.99, "sz": " S, M, L", "pp": 0.0, "sx": "M", "nm": "<a href=\"http://www.decathlon.pl/spodenki-adidas-douario-id_8406789.html\">Spodenki fitness ADIDAS</a>", "dc": 26, "sc": "Odzie\u00c5\u00bc Fitness Cardio", "or": "Nowa", "op": 94.99}, {"pr": 14.99, "sz": " XS, S, M, L", "pp": 0.0, "sx": "F", "nm": "<a href=\"http://www.decathlon.pl/stanik-fitness-kardio-100-id_8397101.html\">Stanik fitness CONFORT DOMYOS</a>", "dc": 25, "sc": "Odzie\u00c5\u00bc Fitness Cardio", "or": "Nowa", "op": 19.99}, {"pr": 124.99, "sz": " 36, 37, 38, 39, 40, 41, 42", "pp": 0.0, "sx": "F", "nm": "<a href=\"http://www.decathlon.pl/buty-fitness-kardio-500-id_8484796.html\">Buty fitness kardio 500 mid damskie DOMYOS</a>", "dc": 22, "sc": "Odzie\u00c5\u00bc Fitness Cardio", "or": "Nowa", "op": 159.99}, {"pr": 109.99, "sz": " 40, 41, 42, 43, 44, 45, 46", "pp": 0.0, "sx": "M", "nm": "<a href=\"http://www.decathlon.pl/buty-fitness-kardio-500-id_8491836.html\">Buty fitness kardio 500 m\u0119skie DOMYOS</a>", "dc": 21, "sc": "Odzie\u00c5\u00bc Fitness Cardio", "or": "Nowa", "op": 139.99}, {"pr": 39.99, "sz": " M, L, XL, 2XL", "pp": 0.0, "sx": "M", "nm": "<a href=\"http://www.decathlon.pl/koszulka-cardio-fts-500-id_8484970.html\">Koszulka fitness kardio kr\u00f3tki r\u0119kaw FTS 500 m\u0119ska DOMYOS</a>", "dc": 20, "sc": "Odzie\u00c5\u00bc Fitness Cardio", "or": "Nowa", "op": 49.99}, {"pr": 14.99, "sz": " 40", "pp": 14.99, "sx": "F", "nm": "<a href=\"http://www.decathlon.pl/koszulka-fitness-cardio-100-id_8484710.html\">Koszulka fitness kardio kr\u00f3tki r\u0119kaw 100 damska DOMYOS</a>", "dc": 25, "sc": "Odzie\u00c5\u00bc Fitness Cardio", "or": "Powr\u00f3t", "op": 19.99}, {"pr": 54.99, "sz": " ", "pp": 0.0, "sx": "U", "nm": "<a href=\"http://www.decathlon.pl/torba-fitness-30l-domyos-id_8484763.html\">Torba fitness kardio 30l DOMYOS</a>", "dc": 31, "sc": "Buty i akcesoria Fitness", "or": "Nowa", "op": 79.99}, {"pr": 49.99, "sz": " 25, 26, 27, 28, 29, 30", "pp": 49.99, "sx": "J", "nm": "<a href=\"http://www.decathlon.pl/buty-i-move-id_8393683.html\">Buty I MOVE  DOMYOS</a>", "dc": 38, "sc": "Buty i akcesoria Fitness", "or": "Powr\u00f3t", "op": 79.99}, {"pr": 69.99, "sz": " 35, 36, 37, 38, 39, 40, 41", "pp": 69.99, "sx": "U", "nm": "<a href=\"http://www.decathlon.pl/buty-vulca-canvas-l-jungle-id_8382299.html\">Niskie buty skate-longboard VULCA CANVAS L JUNGLE OXELO</a>", "dc": 30, "sc": "Buty", "or": "Powr\u00f3t", "op": 99.99}, {"pr": 49.99, "sz": " M, L, XL, 2XL", "pp": 0.0, "sx": "M", "nm": "<a href=\"http://www.decathlon.pl/koszulka-kiprun-id_8394813.html\">Koszulka do biegania d\u0142ugi r\u0119kaw SKINCARE Kiprun m\u0119ska KALENJI</a>", "dc": 29, "sc": "Odzie\u00c5\u00bc do biegania", "or": "Nowa", "op": 69.99}, {"pr": 29.99, "sz": " M, L, XL", "pp": 0.0, "sx": "M", "nm": "<a href=\"http://www.decathlon.pl/spodenki-kiprun-split--id_8488095.html\">Spodenki do biegania KIPRUN SPLIT m\u0119skie KALENJI</a>", "dc": 25, "sc": "Odzie\u00c5\u00bc do biegania", "or": "Nowa", "op": 39.99}, {"pr": 44.99, "sz": " S, M, L, XL, 2XL", "pp": 0.0, "sx": "M", "nm": "<a href=\"http://www.decathlon.pl/koszulka-kiprun-id_8488102.html\">Koszulka do biegania bez r\u0119kaw\u00f3w KIPRUN m\u0119ska KALENJI</a>", "dc": 25, "sc": "Odzie\u00c5\u00bc do biegania", "or": "Nowa", "op": 59.99}, {"pr": 39.99, "sz": " S, M, L, XL", "pp": 0.0, "sx": "F", "nm": "<a href=\"http://www.decathlon.pl/koszulka-kiprun-care-id_8488503.html\">Koszulka do biegania KIPRUN CARE damska KALENJI</a>", "dc": 20, "sc": "Odzie\u00c5\u00bc do biegania", "or": "Nowa", "op": 49.99}, {"pr": 24.99, "sz": " 48", "pp": 0.0, "sx": "F", "nm": "<a href=\"http://www.decathlon.pl/bluza-run-warm-id_8394791.html\">Bluza biegania RUN WARM damska KALENJI</a>", "dc": 17, "sc": "Odzie\u00c5\u00bc do biegania", "or": "Nowa", "op": 29.99}, {"pr": 49.99, "sz": " M, L, XL, 2XL", "pp": 0.0, "sx": "M", "nm": "<a href=\"http://www.decathlon.pl/spodenki-kiprun-light-id_8488091.html\">Spodenki do biegania KIPRUN LIGHT+ m\u0119skie KALENJI</a>", "dc": 17, "sc": "Odzie\u00c5\u00bc do biegania", "or": "Nowa", "op": 59.99}, {"pr": 24.99, "sz": " 6 LAT, 10 LAT, 12 LAT, 14 LAT", "pp": 0.0, "sx": "J", "nm": "<a href=\"http://www.decathlon.pl/koszulka-run-dry-id_8488232.html\">Koszulka do biegania bez r\u0119kaw\u00f3w RUN DRY + dla dzieci KALENJI</a>", "dc": 17, "sc": "Odzie\u00c5\u00bc do biegania", "or": "Nowa", "op": 29.99}, {"pr": 49.99, "sz": " 2XS, XS, S, M, L", "pp": 0.0, "sx": "F", "nm": "<a href=\"http://www.decathlon.pl/spodenki-kiprun-id_8488261.html\">Spodenki do biegania KIPRUN damskie KALENJI</a>", "dc": 17, "sc": "Odzie\u00c5\u00bc do biegania", "or": "Nowa", "op": 59.99}, {"pr": 14.99, "sz": " 2XL", "pp": 14.99, "sx": "M", "nm": "<a href=\"http://www.decathlon.pl/spodenki-split-kiprun-id_8381649.html\">Spodenki do biegania Split Kiprun m\u0119skie KALENJI</a>", "dc": 63, "sc": "Odzie\u00c5\u00bc do biegania", "or": "Powr\u00f3t", "op": 39.99}, {"pr": 11.99, "sz": " ", "pp": 11.99, "sx": "U", "nm": "<a href=\"http://www.decathlon.pl/czapka-id_8393528.html\">Czapka do biegania KALENJI</a>", "dc": 40, "sc": "Akcesoria do biegania", "or": "Powr\u00f3t", "op": 19.99}, {"pr": 9.99, "sz": " ", "pp": 9.99, "sx": "U", "nm": "<a href=\"http://www.decathlon.pl/pas-na-butelk-id_8487831.html\">Pas na butelk\u0119 do biegania KALENJI</a>", "dc": 33, "sc": "Akcesoria do biegania", "or": "Powr\u00f3t", "op": 14.99}, {"pr": 59.99, "sz": " 35, 36, 37, 38, 39", "pp": 0.0, "sx": "J", "nm": "<a href=\"http://www.decathlon.pl/buty-ekiden-active-id_8380932.html\">Buty do biegania Run ACTIVE dla dzieci KALENJI</a>", "dc": 14, "sc": "Buty do biegania dla dzieci", "or": "Nowa", "op": 69.99}, {"pr": 19.99, "sz": " M, L", "pp": 19.99, "sx": "M", "nm": "<a href=\"http://www.decathlon.pl/bluza-ekiden-warm-id_8394840.html\">Bluza do biegania Ekiden Warm m\u0119ska KALENJI</a>", "dc": 33, "sc": "Odzie\u00c5\u00bc do biegania na ch\u00c5\u0082odne i zimne dni", "or": "Powr\u00f3t", "op": 29.99}, {"pr": 19.99, "sz": " ", "pp": 0.0, "sx": "U", "nm": "<a href=\"http://www.decathlon.pl/bransoletka-do-charge-2-s-id_8405873.html\">Bransoletka do CHARGE 2 (S) FITBIT</a>", "dc": 85, "sc": "Zegarki do biegania, pulsometry, GPS", "or": "Nowa", "op": 129.99}, {"pr": 899.99, "sz": " ", "pp": 0.0, "sx": "U", "nm": "<a href=\"http://www.decathlon.pl/zegarek-adventurer-cardio-id_8388559.html\">Zegarek sportowy GPS Adventurer cardio + music rozm. L TOMTOM</a>", "dc": 10, "sc": "Zegarki do biegania, pulsometry, GPS", "or": "Nowa", "op": 999.99}, {"pr": 39.99, "sz": " ", "pp": 0.0, "sx": "U", "nm": "<a href=\"http://www.decathlon.pl/torba-pywacka-swimy-30-l-id_8402522.html\">Torba p\u0142ywacka SWIMY 30 L NABAIJI</a>", "dc": 20, "sc": "Stroje p\u00c5\u0082ywackie", "or": "Nowa", "op": 49.99}, {"pr": 93.0, "sz": " ", "pp": 89.99, "sx": "U", "nm": "<a href=\"http://www.decathlon.pl/odtwarzacz-mp3-swimmusic-100-id_8505756.html\">Szczelny odtwarzacz p\u0142ywacki MP3 SwimMusic 100 NABAIJI</a>", "dc": 28, "sc": "Stroje p\u00c5\u0082ywackie", "or": "Wy\u017csza cena z 89.99", "op": 129.99}, {"pr": 12.0, "sz": " 12 MOIS", "pp": 13.0, "sx": "U", "nm": "<a href=\"http://www.decathlon.pl/bokserki-titou-all-wav-baby-id_8388018.html\">Bokserki p\u0142ywackie titou all wav dla malucha NABAIJI</a>", "dc": 40, "sc": "Stroje p\u00c5\u0082ywackie", "or": "Ni\u017csza cena z 13.0", "op": 19.99}, {"pr": 34.99, "sz": " M, L, XL, 2XL", "pp": 0.0, "sx": "M", "nm": "<a href=\"http://www.decathlon.pl/spodenki-bbs-900-id_8403543.html\">Spodenki surfing BBS 900 OLAIAN</a>", "dc": 56, "sc": "Kostiumy, odzie\u00c5\u00bc, obuwie", "or": "Nowa", "op": 79.99}, {"pr": 9.99, "sz": " 35/36, 37/38, 39/40", "pp": 0.0, "sx": "F", "nm": "<a href=\"http://www.decathlon.pl/japonki-to-150-palma-id_8486182.html\">Japonki TO 150 Palma damskie OLAIAN</a>", "dc": 50, "sc": "Kostiumy, odzie\u00c5\u00bc, obuwie", "or": "Nowa", "op": 19.99}, {"pr": 19.99, "sz": " 36 B, 38 B, 40 C, 42 C, 46 D", "pp": 0.0, "sx": "F", "nm": "<a href=\"http://www.decathlon.pl/gora-kostiumu-mae-dima-id_8486288.html\">G\u00f3ra kostiumu k\u0105pielowego MAE DIMA damska OLAIAN</a>", "dc": 50, "sc": "Kostiumy, odzie\u00c5\u00bc, obuwie", "or": "Nowa", "op": 39.99}, {"pr": 7.99, "sz": " ", "pp": 0.0, "sx": "U", "nm": "<a href=\"http://www.decathlon.pl/rcznik-basic-s-id_8354435.html\">R\u0119cznik Basic S 50 x 90 cm OLAIAN</a>", "dc": 47, "sc": "Kostiumy, odzie\u00c5\u00bc, obuwie", "or": "Nowa", "op": 14.99}, {"pr": 9.99, "sz": " 31/32, 33/34, 35/36, 37/38", "pp": 0.0, "sx": "J", "nm": "<a href=\"http://www.decathlon.pl/japonki-to-150-patch-jr-id_8486197.html\">Japonki TO 150 Patch dla dzieci OLAIAN</a>", "dc": 44, "sc": "Kostiumy, odzie\u00c5\u00bc, obuwie", "or": "Nowa", "op": 17.99}, {"pr": 39.99, "sz": " 40, 42, 44", "pp": 0.0, "sx": "F", "nm": "<a href=\"http://www.decathlon.pl/kostium-1cz-cori-bali--id_8403487.html\">Kostium jednocz\u0119\u015bciowy CORI BALI damski OLAIAN</a>", "dc": 43, "sc": "Kostiumy, odzie\u00c5\u00bc, obuwie", "or": "Nowa", "op": 69.99}, {"pr": 34.99, "sz": " ", "pp": 0.0, "sx": "J", "nm": "<a href=\"http://www.decathlon.pl/ponczo-pon-due-stripes-jr-id_8330777.html\">Ponczo surfing PON DU\u017bE Stripes dla dzieci OLAIAN</a>", "dc": 42, "sc": "Kostiumy, odzie\u00c5\u00bc, obuwie", "or": "Nowa", "op": 59.99}, {"pr": 34.99, "sz": " 8 LAT, 10 LAT, 12 LAT, 14 LAT, 16 LAT", "pp": 0.0, "sx": "J", "nm": "<a href=\"http://www.decathlon.pl/kostium-1cz-rio-naimi-jr-id_8486030.html\">Kostium jednocz\u0119\u015bciowy RIO NAIMI dla dzieci OLAIAN</a>", "dc": 42, "sc": "Kostiumy, odzie\u00c5\u00bc, obuwie", "or": "Nowa", "op": 59.99}, {"pr": 29.99, "sz": " ", "pp": 0.0, "sx": "J", "nm": "<a href=\"http://www.decathlon.pl/ponczo-pon-mae-seya-jr-id_8403297.html\">Ponczo surfing PON MA\u0141E Seya dla dzieci OLAIAN</a>", "dc": 40, "sc": "Kostiumy, odzie\u00c5\u00bc, obuwie", "or": "Nowa", "op": 49.99}, {"pr": 29.99, "sz": " 27/28 .,,, 29/30, 31/32, 33/34, 35/36, 37/38", "pp": 0.0, "sx": "J", "nm": "<a href=\"http://www.decathlon.pl/japonki-to-550-jr-id_8403349.html\">Japonki TO 550 dla dzieci OLAIAN</a>", "dc": 40, "sc": "Kostiumy, odzie\u00c5\u00bc, obuwie", "or": "Nowa", "op": 49.99}, {"pr": 29.99, "sz": " 35/36, 37/38, 39/40, 41/42", "pp": 0.0, "sx": "F", "nm": "<a href=\"http://www.decathlon.pl/japonki-to-550-id_8403381.html\">Japonki TO 550 damskie OLAIAN</a>", "dc": 40, "sc": "Kostiumy, odzie\u00c5\u00bc, obuwie", "or": "Nowa", "op": 49.99}, {"pr": 29.99, "sz": " EU:70A FR:85A, EU:70B FR:85B, EU:75B FR:90B, EU:75C FR:90C, EU:80D FR:95D", "pp": 0.0, "sx": "F", "nm": "<a href=\"http://www.decathlon.pl/gora-kostiumu-laeti-dima-id_8403468.html\">G\u00f3ra kostiumu k\u0105pielowego LAETI DIMA damska OLAIAN</a>", "dc": 40, "sc": "Kostiumy, odzie\u00c5\u00bc, obuwie", "or": "Nowa", "op": 49.99}, {"pr": 29.99, "sz": " S, M, L, XL, 2XL", "pp": 0.0, "sx": "M", "nm": "<a href=\"http://www.decathlon.pl/spodenki-bbs-500-id_8403532.html\">Spodenki surfing kr\u00f3tkie BBS 500 OLAIAN</a>", "dc": 40, "sc": "Kostiumy, odzie\u00c5\u00bc, obuwie", "or": "Nowa", "op": 49.99}, {"pr": 119.99, "sz": " S, M", "pp": 0.0, "sx": "M", "nm": "<a href=\"http://www.decathlon.pl/spodenki-mix-nstripes-id_8408692.html\">Spodenki surfing MIX N'STRIPES m\u0119skie QUIKSILVER</a>", "dc": 40, "sc": "Kostiumy, odzie\u00c5\u00bc, obuwie", "or": "Nowa", "op": 199.99}, {"pr": 42.0, "sz": " EU:75B FR:90B, EU:75C FR:90C, EU:75E FR:90E, EU:80C FR:95C, EU:80D FR:95D", "pp": 0.0, "sx": "F", "nm": "<a href=\"http://www.decathlon.pl/gora-kostiumu-lea-bali-id_8486299.html\">G\u00f3ra kostiumu k\u0105pielowego LEA BALI damska OLAIAN</a>", "dc": 40, "sc": "Kostiumy, odzie\u00c5\u00bc, obuwie", "or": "Nowa", "op": 69.99}, {"pr": 29.99, "sz": " 38, 40", "pp": 0.0, "sx": "F", "nm": "<a href=\"http://www.decathlon.pl/do-kostiumu-vaiana-shibo-id_8502393.html\">D\u00f3\u0142 kostiumu k\u0105pielowego VAIANA SHIBO damski OLAIAN</a>", "dc": 40, "sc": "Kostiumy, odzie\u00c5\u00bc, obuwie", "or": "Nowa", "op": 49.99}, {"pr": 49.99, "sz": " ", "pp": 0.0, "sx": "U", "nm": "<a href=\"http://www.decathlon.pl/ponczo-pon-celtic-id_8354484.html\">Ponczo surfing PON Celtic OLAIAN</a>", "dc": 38, "sc": "Kostiumy, odzie\u00c5\u00bc, obuwie", "or": "Nowa", "op": 79.99}, {"pr": 24.99, "sz": " ", "pp": 0.0, "sx": "U", "nm": "<a href=\"http://www.decathlon.pl/rcznik-basic-l-fake-id_8403315.html\">R\u0119cznik Basic L Fake 145 x 85 cm OLAIAN</a>", "dc": 38, "sc": "Kostiumy, odzie\u00c5\u00bc, obuwie", "or": "Nowa", "op": 39.99}, {"pr": 24.99, "sz": " 27/28 .,,, 29/30, 31/32, 33/34, 35/36, 37/38", "pp": 0.0, "sx": "J", "nm": "<a href=\"http://www.decathlon.pl/japonki-to-500-evo-jr-id_8403393.html\">Japonki TO 500 Evo dla dzieci OLAIAN</a>", "dc": 38, "sc": "Kostiumy, odzie\u00c5\u00bc, obuwie", "or": "Nowa", "op": 39.99}, {"pr": 24.99, "sz": " 36, 38, 40, 42, 44, 46", "pp": 0.0, "sx": "F", "nm": "<a href=\"http://www.decathlon.pl/do-kostiumu-nina-pop-id_8486302.html\">D\u00f3\u0142 kostiumu k\u0105pielowego NINA POP damski OLAIAN</a>", "dc": 38, "sc": "Kostiumy, odzie\u00c5\u00bc, obuwie", "or": "Nowa", "op": 39.99}, {"pr": 12.99, "sz": " 6 MIESIACE, 12 MIESIACE, 18 MIESIACE, 2 LATA, 3 LATA, 4 LATA", "pp": 0.0, "sx": "J", "nm": "<a href=\"http://www.decathlon.pl/spodenki-uv-100-baby-id_8403439.html\">Spodenki UV surfing 100 dla malucha OLAIAN</a>", "dc": 35, "sc": "Kostiumy, odzie\u00c5\u00bc, obuwie", "or": "Nowa", "op": 19.99}, {"pr": 129.99, "sz": " M", "pp": 0.0, "sx": "M", "nm": "<a href=\"http://www.decathlon.pl/spodenki-mix-nstripes-id_8408693.html\">Spodenki surfing MIX N'STRIPES m\u0119skie QUIKSILVER</a>", "dc": 35, "sc": "Kostiumy, odzie\u00c5\u00bc, obuwie", "or": "Nowa", "op": 199.99}, {"pr": 12.99, "sz": " 39/40, 41/42, 43/44", "pp": 0.0, "sx": "M", "nm": "<a href=\"http://www.decathlon.pl/japonki-to-150-geo-id_8486255.html\">Japonki TO 150 Geo m\u0119skie OLAIAN</a>", "dc": 35, "sc": "Kostiumy, odzie\u00c5\u00bc, obuwie", "or": "Nowa", "op": 19.99}, {"pr": 79.99, "sz": " S, M, L, XL, 2XL", "pp": 0.0, "sx": "M", "nm": "<a href=\"http://www.decathlon.pl/spodenki-sbs-900-intensity-id_8485909.html\">Spodenki surfing d\u0142ugie SBS 900 Intensity OLAIAN</a>", "dc": 33, "sc": "Kostiumy, odzie\u00c5\u00bc, obuwie", "or": "Nowa", "op": 119.99}, {"pr": 39.99, "sz": " 8 LAT, 10 LAT, 12 LAT, 14 LAT", "pp": 0.0, "sx": "J", "nm": "<a href=\"http://www.decathlon.pl/spodenki-sbs-500-foam-jr-id_8485983.html\">Spodenki surfing d\u0142ugie SBS 500 Foam dla dzieci OLAIAN</a>", "dc": 33, "sc": "Kostiumy, odzie\u00c5\u00bc, obuwie", "or": "Nowa", "op": 59.99}, {"pr": 29.99, "sz": " S, M, L, XL, 2XL", "pp": 0.0, "sx": "M", "nm": "<a href=\"http://www.decathlon.pl/spodenki-sbs-100-cloud-id_8486132.html\">Spodenki surfing d\u0142ugie 100 Cloud OLAIAN</a>", "dc": 33, "sc": "Kostiumy, odzie\u00c5\u00bc, obuwie", "or": "Nowa", "op": 44.99}, {"pr": 34.99, "sz": " EU:70A FR:85A, EU:70B FR:85B, EU:75B FR:90B, EU:75C FR:90C, EU:80C FR:95C, EU:80D FR:95D", "pp": 0.0, "sx": "F", "nm": "<a href=\"http://www.decathlon.pl/gora-kostiumu-laeti-mosaica-id_8384655.html\">G\u00f3ra kostiumu k\u0105pielowego LAETI MOSAICA damska OLAIAN</a>", "dc": 30, "sc": "Kostiumy, odzie\u00c5\u00bc, obuwie", "or": "Nowa", "op": 49.99}, {"pr": 17.99, "sz": " 4 LATA, 6 LAT, 8 LAT, 10 LAT", "pp": 0.0, "sx": "J", "nm": "<a href=\"http://www.decathlon.pl/spodenki-bbs-100-block-jr-id_8486097.html\">Spodenki surfing kr\u00f3tkie BBS 100 Block dla dzieci OLAIAN</a>", "dc": 28, "sc": "Kostiumy, odzie\u00c5\u00bc, obuwie", "or": "Nowa", "op": 24.99}, {"pr": 29.99, "sz": " 37/38, 39/40", "pp": 0.0, "sx": "F", "nm": "<a href=\"http://www.decathlon.pl/japonki-to-500-pop-id_8403329.html\">Japonki TO 500 Pop damskie OLAIAN</a>", "dc": 25, "sc": "Kostiumy, odzie\u00c5\u00bc, obuwie", "or": "Nowa", "op": 39.99}, {"pr": 29.99, "sz": " 36, 38, 40, 42, 46", "pp": 0.0, "sx": "F", "nm": "<a href=\"http://www.decathlon.pl/do-kostiumu-sabi-terra-id_8403472.html\">D\u00f3\u0142 kostiumu k\u0105pielowego SABI TERRA damski OLAIAN</a>", "dc": 25, "sc": "Kostiumy, odzie\u00c5\u00bc, obuwie", "or": "Nowa", "op": 39.99}, {"pr": 59.99, "sz": " 40, 42, 44, 46, 48", "pp": 0.0, "sx": "F", "nm": "<a href=\"http://www.decathlon.pl/kostium-1cz-clea-terra-id_8403490.html\">Kostium jednocz\u0119\u015bciowy CLEA TERRA damski OLAIAN</a>", "dc": 25, "sc": "Kostiumy, odzie\u00c5\u00bc, obuwie", "or": "Nowa", "op": 79.99}, {"pr": 29.99, "sz": " EU:75C FR:90C", "pp": 0.0, "sx": "F", "nm": "<a href=\"http://www.decathlon.pl/gora-kostiumu-andrea-wave-id_8403523.html\">G\u00f3ra kostiumu k\u0105pielowego ANDREA WAVE damska OLAIAN</a>", "dc": 25, "sc": "Kostiumy, odzie\u00c5\u00bc, obuwie", "or": "Nowa", "op": 39.99}, {"pr": 14.99, "sz": " 8 LAT, 10 LAT, 12 LAT, 14 LAT, 16 LAT", "pp": 0.0, "sx": "J", "nm": "<a href=\"http://www.decathlon.pl/kostium-2cz-taloo-cali-jr-id_8485919.html\">Kostium dwucz\u0119\u015bciowy TALOO CALI dla dzieci OLAIAN</a>", "dc": 25, "sc": "Kostiumy, odzie\u00c5\u00bc, obuwie", "or": "Nowa", "op": 19.99}, {"pr": 29.99, "sz": " 4 LATA, 5 ANS, 6 LAT, 8 LAT, 10 LAT", "pp": 0.0, "sx": "J", "nm": "<a href=\"http://www.decathlon.pl/kostium-1cz-hanna-happy-jr-id_8486058.html\">Kostium jednocz\u0119\u015bciowy HANNA HAPPY dla dzieci OLAIAN</a>", "dc": 25, "sc": "Kostiumy, odzie\u00c5\u00bc, obuwie", "or": "Nowa", "op": 39.99}, {"pr": 29.99, "sz": " 36, 38, 40, 44, 46", "pp": 0.0, "sx": "F", "nm": "<a href=\"http://www.decathlon.pl/szorty-surfing-tini-mira-id_8504505.html\">Szorty surfing TINI MIRA damskie OLAIAN</a>", "dc": 25, "sc": "Kostiumy, odzie\u00c5\u00bc, obuwie", "or": "Nowa", "op": 39.99}, {"pr": 15.99, "sz": " 6-12 MIESIACE, 18 MIESIACE - 2 LATA", "pp": 0.0, "sx": "J", "nm": "<a href=\"http://www.decathlon.pl/kapelusz-uv-baby-id_8384486.html\">Kapelusz UV surfing dla malucha OLAIAN</a>", "dc": 20, "sc": "Kostiumy, odzie\u00c5\u00bc, obuwie", "or": "Nowa", "op": 19.99}, {"pr": 39.99, "sz": " 39/40, 41/42, 43/44, 45/46, 47/48", "pp": 0.0, "sx": "M", "nm": "<a href=\"http://www.decathlon.pl/japonki-to-550-id_8403338.html\">Japonki TO 550 m\u0119skie OLAIAN</a>", "dc": 20, "sc": "Kostiumy, odzie\u00c5\u00bc, obuwie", "or": "Nowa", "op": 49.99}, {"pr": 39.99, "sz": " EU:70A FR:85A, EU:70B FR:85B, EU:75B FR:90B, EU:75C FR:90C, EU:80C FR:95C, EU:80D FR:95D", "pp": 0.0, "sx": "F", "nm": "<a href=\"http://www.decathlon.pl/gora-kostiumu-andrea-shibo-id_8486405.html\">G\u00f3ra kostiumu k\u0105pielowego ANDREA SHIBO damska OLAIAN</a>", "dc": 20, "sc": "Kostiumy, odzie\u00c5\u00bc, obuwie", "or": "Nowa", "op": 49.99}, {"pr": 12.99, "sz": " 4 LATA, 5 ANS, 6 LAT, 10 LAT", "pp": 0.0, "sx": "J", "nm": "<a href=\"http://www.decathlon.pl/kostium-dwuczciowy-dla-dzieci-basic-ag-cro-id_8201528.html\">Kostium dwucz\u0119\u015bciowy BALI dla dzieci OLAIAN</a>", "dc": 19, "sc": "Kostiumy, odzie\u00c5\u00bc, obuwie", "or": "Nowa", "op": 15.99}, {"pr": 12.99, "sz": " 36, 38, 40, 42, 44", "pp": 0.0, "sx": "F", "nm": "<a href=\"http://www.decathlon.pl/do-kostiumu-sofy-mira-id_8486397.html\">D\u00f3\u0142 kostiumu k\u0105pielowego SOFY MIRA damski OLAIAN</a>", "dc": 19, "sc": "Kostiumy, odzie\u00c5\u00bc, obuwie", "or": "Nowa", "op": 15.99}, {"pr": 39.99, "sz": " ", "pp": 39.99, "sx": "J", "nm": "<a href=\"http://www.decathlon.pl/ponczo-pon-due-camo-jr-id_8486677.html\">Ponczo surfing PON DU\u017bE Camo dla dzieci OLAIAN</a>", "dc": 33, "sc": "Kostiumy, odzie\u00c5\u00bc, obuwie", "or": "Powr\u00f3t", "op": 59.99}, {"pr": 69.99, "sz": " 36, 38, 40, 42, 44, 46, 48", "pp": 49.99, "sx": "F", "nm": "<a href=\"http://www.decathlon.pl/koszula-eglarska-100-id_8356344.html\">Koszula \u017ceglarska 100 damska TRIBORD</a>", "dc": 30, "sc": "Kostiumy, odzie\u00c5\u00bc, obuwie", "or": "Powr\u00f3t z wy\u017csz\u0105 cen\u0105 z 49.99", "op": 99.99}, {"pr": 39.99, "sz": " 36/37", "pp": 29.99, "sx": "J", "nm": "<a href=\"http://www.decathlon.pl/sanday-s-500-jr-id_8332141.html\">Sanda\u0142y S 500 dla dzieci TRIBORD</a>", "dc": 20, "sc": "Kostiumy, odzie\u00c5\u00bc, obuwie", "or": "Powr\u00f3t z wy\u017csz\u0105 cen\u0105 z 29.99", "op": 49.99}, {"pr": 19.99, "sz": " 36, 38, 40, 42, 44", "pp": 0.0, "sx": "F", "nm": "<a href=\"http://www.decathlon.pl/do-kostiumu-sofy-pop-id_8486399.html\">D\u00f3\u0142 kostiumu k\u0105pielowego SOFY POP damski OLAIAN</a>", "dc": 33, "sc": "Bikini", "or": "Nowa", "op": 29.99}, {"pr": 19.99, "sz": " 36, 38, 40, 42, 44, 46", "pp": 0.0, "sx": "F", "nm": "<a href=\"http://www.decathlon.pl/do-kostiumu-sofy-dima-id_8486400.html\">D\u00f3\u0142 kostiumu k\u0105pielowego SOFY DIMA damski OLAIAN</a>", "dc": 33, "sc": "Bikini", "or": "Nowa", "op": 29.99}, {"pr": 19.99, "sz": " 36, 38, 40, 42, 44, 46", "pp": 0.0, "sx": "F", "nm": "<a href=\"http://www.decathlon.pl/do-kostiumu-sofy-bali-id_8486401.html\">D\u00f3\u0142 kostiumu k\u0105pielowego SOFY BALI damski OLAIAN</a>", "dc": 33, "sc": "Bikini", "or": "Nowa", "op": 29.99}, {"pr": 34.99, "sz": " EU:70A FR:85A, EU:70B FR:85B, EU:75B FR:90B, EU:75C FR:90C, EU:80C FR:95C, EU:80D FR:95D", "pp": 0.0, "sx": "F", "nm": "<a href=\"http://www.decathlon.pl/gora-kostiumu-laeti-pop-id_8403465.html\">G\u00f3ra kostiumu k\u0105pielowego LAETI POP damska OLAIAN</a>", "dc": 30, "sc": "Bikini", "or": "Nowa", "op": 49.99}, {"pr": 49.99, "sz": " 38, 40, 42, 44, 46, 50", "pp": 0.0, "sx": "F", "nm": "<a href=\"http://www.decathlon.pl/kostium-1cz-cori-terra-id_8403488.html\">Kostium jednocz\u0119\u015bciowy CORI TERRA damski OLAIAN</a>", "dc": 29, "sc": "Bikini", "or": "Nowa", "op": 69.99}, {"pr": 49.99, "sz": " EU:75B FR:90B, EU:75C FR:90C, EU:80C FR:95C, EU:80D FR:95D", "pp": 0.0, "sx": "F", "nm": "<a href=\"http://www.decathlon.pl/gora-kostiumu-lea-terra-id_8486301.html\">G\u00f3ra kostiumu k\u0105pielowego LEA TERRA damska OLAIAN</a>", "dc": 29, "sc": "Bikini", "or": "Nowa", "op": 69.99}, {"pr": 29.99, "sz": " EU:75B FR:90B, EU:75C FR:90C, EU:80C FR:95C", "pp": 0.0, "sx": "F", "nm": "<a href=\"http://www.decathlon.pl/gora-kostiumu-andrea-wave-id_8403522.html\">G\u00f3ra kostiumu k\u0105pielowego ANDREA WAVE damska OLAIAN</a>", "dc": 25, "sc": "Bikini", "or": "Nowa", "op": 39.99}, {"pr": 29.99, "sz": " 36 B, 38 B, 40 C, 42 C, 44 D, 46 D", "pp": 0.0, "sx": "F", "nm": "<a href=\"http://www.decathlon.pl/gora-kostiumu-mae-pop-id_8486287.html\">G\u00f3ra kostiumu k\u0105pielowego MAE POP damska OLAIAN</a>", "dc": 25, "sc": "Bikini", "or": "Nowa", "op": 39.99}, {"pr": 29.99, "sz": " 36 B, 40 C, 42 C, 44 D, 46 D", "pp": 0.0, "sx": "F", "nm": "<a href=\"http://www.decathlon.pl/gora-kostiumu-mae-bali-id_8486291.html\">G\u00f3ra kostiumu k\u0105pielowego MAE BALI damska OLAIAN</a>", "dc": 25, "sc": "Bikini", "or": "Nowa", "op": 39.99}, {"pr": 29.99, "sz": " 38, 40, 42, 46", "pp": 0.0, "sx": "F", "nm": "<a href=\"http://www.decathlon.pl/do-kostiumu-nina-terra-id_8486307.html\">D\u00f3\u0142 kostiumu k\u0105pielowego NINA TERRA damski OLAIAN</a>", "dc": 25, "sc": "Bikini", "or": "Nowa", "op": 39.99}, {"pr": 39.99, "sz": " S, M, L, XL, 2XL", "pp": 0.0, "sx": "M", "nm": "<a href=\"http://www.decathlon.pl/spodenki-bbs-900-deep--id_8403542.html\">Spodenki surfing BBS 900 Deep OLAIAN</a>", "dc": 50, "sc": "Boardshorty m\u00c4\u0099skie", "or": "Nowa", "op": 79.99}, {"pr": 39.99, "sz": " S, M, L, XL, 2XL", "pp": 0.0, "sx": "M", "nm": "<a href=\"http://www.decathlon.pl/spodenki-bbs-900-light-id_8486128.html\">Spodenki surfing BBS 900 Light OLAIAN</a>", "dc": 50, "sc": "Boardshorty m\u00c4\u0099skie", "or": "Nowa", "op": 79.99}, {"pr": 29.99, "sz": " S, M, L, XL, 2XL", "pp": 0.0, "sx": "M", "nm": "<a href=\"http://www.decathlon.pl/spodenki-sbs-100-free-id_8486133.html\">Spodenki surfing d\u0142ugie SBS 100 Free OLAIAN</a>", "dc": 33, "sc": "Boardshorty m\u00c4\u0099skie", "or": "Nowa", "op": 44.99}, {"pr": 34.99, "sz": " S, M, L, XL, 2XL", "pp": 0.0, "sx": "M", "nm": "<a href=\"http://www.decathlon.pl/spodenki-bbs-500-foam-id_8486125.html\">Spodenki surfing kr\u00f3tkie BBS 500 Foam OLAIAN</a>", "dc": 30, "sc": "Boardshorty m\u00c4\u0099skie", "or": "Nowa", "op": 49.99}, {"pr": 49.99, "sz": " S, M, L, XL, 2XL", "pp": 0.0, "sx": "M", "nm": "<a href=\"http://www.decathlon.pl/spodenki-sbs-500-best-id_8485904.html\">Spodenki surfing d\u0142ugie SBS 500 Best OLAIAN</a>", "dc": 29, "sc": "Boardshorty m\u00c4\u0099skie", "or": "Nowa", "op": 69.99}, {"pr": 49.99, "sz": " S, M, L, XL", "pp": 0.0, "sx": "M", "nm": "<a href=\"http://www.decathlon.pl/spodenki-sbs-500-best-id_8485905.html\">Spodenki surfing d\u0142ugie SBS 500 Best OLAIAN</a>", "dc": 29, "sc": "Boardshorty m\u00c4\u0099skie", "or": "Nowa", "op": 69.99}, {"pr": 59.99, "sz": " S, M, L, XL, 2XL", "pp": 0.0, "sx": "M", "nm": "<a href=\"http://www.decathlon.pl/spodenki-bbs-900-deep-id_8403540.html\">Spodenki surfing BBS 900 Deep OLAIAN</a>", "dc": 25, "sc": "Boardshorty m\u00c4\u0099skie", "or": "Nowa", "op": 79.99}, {"pr": 59.99, "sz": " S, M, L, XL, 2XL", "pp": 0.0, "sx": "M", "nm": "<a href=\"http://www.decathlon.pl/spodenki-bbs-900-id_8485886.html\">Spodenki surfing BBS 900 OLAIAN</a>", "dc": 25, "sc": "Boardshorty m\u00c4\u0099skie", "or": "Nowa", "op": 79.99}, {"pr": 89.99, "sz": " S, M, L, XL", "pp": 0.0, "sx": "M", "nm": "<a href=\"http://www.decathlon.pl/spodenki-sbs-900-symbio-id_8486251.html\">Spodenki surfing d\u0142ugie SBS 900 Symbio OLAIAN</a>", "dc": 25, "sc": "Boardshorty m\u00c4\u0099skie", "or": "Nowa", "op": 119.99}, {"pr": 34.99, "sz": " S, M, L, 2XL", "pp": 0.0, "sx": "M", "nm": "<a href=\"http://www.decathlon.pl/spodenki-sbs-100-stripes-id_8485889.html\">Spodenki surfing d\u0142ugie SBS 100 Stripes OLAIAN</a>", "dc": 22, "sc": "Boardshorty m\u00c4\u0099skie", "or": "Nowa", "op": 44.99}, {"pr": 41.0, "sz": " S, M, L, XL, 2XL", "pp": 0.0, "sx": "M", "nm": "<a href=\"http://www.decathlon.pl/spodenki-bbs-500-lines-id_8486124.html\">Spodenki surfing kr\u00f3tkie BBS 500 Lines OLAIAN</a>", "dc": 18, "sc": "Boardshorty m\u00c4\u0099skie", "or": "Nowa", "op": 49.99}, {"pr": 39.99, "sz": " S, M, L, XL, 2XL", "pp": 0.0, "sx": "M", "nm": "<a href=\"http://www.decathlon.pl/spodenki-sbs-100-stripes-id_8485891.html\">Spodenki surfing d\u0142ugie SBS 100 Stripes OLAIAN</a>", "dc": 11, "sc": "Boardshorty m\u00c4\u0099skie", "or": "Nowa", "op": 44.99}, {"pr": 39.99, "sz": " S, M, L, XL, 2XL", "pp": 0.0, "sx": "M", "nm": "<a href=\"http://www.decathlon.pl/spodenki-sbs-100-free-id_8486134.html\">Spodenki surfing d\u0142ugie SBS 100 Free OLAIAN</a>", "dc": 11, "sc": "Boardshorty m\u00c4\u0099skie", "or": "Nowa", "op": 44.99}, {"pr": 29.99, "sz": " 4 LATA", "pp": 0.0, "sx": "J", "nm": "<a href=\"http://www.decathlon.pl/spodenki-bbs-500-coast-jr-id_8486373.html\">Spodenki surfing kr\u00f3tkie BBS 500 Coast dla dzieci OLAIAN</a>", "dc": 25, "sc": "Boardshorty ch\u00c5\u0082opi\u00c4\u0099ce", "or": "Nowa", "op": 39.99}, {"pr": 19.99, "sz": " 4 LATA, 6 LAT, 8 LAT, 10 LAT", "pp": 0.0, "sx": "J", "nm": "<a href=\"http://www.decathlon.pl/spodenki-bbs-100-line-jr-id_8486104.html\">Spodenki surfing kr\u00f3tkie BBS 100 Line dla dzieci OLAIAN</a>", "dc": 20, "sc": "Boardshorty ch\u00c5\u0082opi\u00c4\u0099ce", "or": "Nowa", "op": 24.99}, {"pr": 24.99, "sz": " 4 LATA, 5 ANS, 6 LAT, 8 LAT, 10 LAT", "pp": 0.0, "sx": "J", "nm": "<a href=\"http://www.decathlon.pl/gora-kostiumu-lali-lagoon-jr-id_8485924.html\">G\u00f3ra kostiumu k\u0105pielowego LALI LAGOON dla dzieci OLAIAN</a>", "dc": 29, "sc": "Kostiumy pla\u00c5\u00bcowe dziewcz\u00c4\u0099ce", "or": "Nowa", "op": 34.99}, {"pr": 24.99, "sz": " 4 LATA, 5 ANS, 6 LAT, 8 LAT, 10 LAT", "pp": 0.0, "sx": "J", "nm": "<a href=\"http://www.decathlon.pl/gora-kostiumu-lali-palmy-jr-id_8485925.html\">G\u00f3ra kostiumu k\u0105pielowego LALI PALMY dla dzieci OLAIAN</a>", "dc": 29, "sc": "Kostiumy pla\u00c5\u00bcowe dziewcz\u00c4\u0099ce", "or": "Nowa", "op": 34.99}, {"pr": 24.99, "sz": " 8 LAT, 10 LAT, 12 LAT, 14 LAT, 16 LAT", "pp": 0.0, "sx": "J", "nm": "<a href=\"http://www.decathlon.pl/gora-kostiumu-lali-cali-jr-id_8485928.html\">G\u00f3ra kostiumu k\u0105pielowego LALI CALI dla dzieci OLAIAN</a>", "dc": 29, "sc": "Kostiumy pla\u00c5\u00bcowe dziewcz\u00c4\u0099ce", "or": "Nowa", "op": 34.99}, {"pr": 24.99, "sz": " 27/28 .,,, 29/30, 31/32, 33/34, 35/36, 37/38", "pp": 0.0, "sx": "J", "nm": "<a href=\"http://www.decathlon.pl/japonki-to-500-jr-id_8386473.html\">Japonki TO 500 dla dzieci OLAIAN</a>", "dc": 38, "sc": "Japonki, buty do wody", "or": "Nowa", "op": 39.99}, {"pr": 39.99, "sz": " 39, 40, 41, 42, 43, 44, 46", "pp": 0.0, "sx": "M", "nm": "<a href=\"http://www.decathlon.pl/buty-plaowe-areeta-id_8403330.html\">Buty pla\u017cowe AREETA m\u0119skie OLAIAN</a>", "dc": 33, "sc": "Japonki, buty do wody", "or": "Nowa", "op": 59.99}, {"pr": 12.99, "sz": " 29/30, 31/32, 33/34, 35/36", "pp": 0.0, "sx": "J", "nm": "<a href=\"http://www.decathlon.pl/japonki-to-150-sunshine-jr-id_8403321.html\">Japonki TO 150 Sunshine dla dzieci OLAIAN</a>", "dc": 28, "sc": "Japonki, buty do wody", "or": "Nowa", "op": 17.99}, {"pr": 29.99, "sz": " 27/28 .,,, 29/30, 31/32, 33/34, 35/36, 37/38", "pp": 0.0, "sx": "J", "nm": "<a href=\"http://www.decathlon.pl/japonki-to-500-coco-jr-id_8358301.html\">Japonki TO 500 Coco dla dzieci OLAIAN</a>", "dc": 25, "sc": "Japonki, buty do wody", "or": "Nowa", "op": 39.99}, {"pr": 29.99, "sz": " 35/36, 37/38, 39/40, 41/42", "pp": 0.0, "sx": "F", "nm": "<a href=\"http://www.decathlon.pl/japonki-to-500-bondi-id_8486625.html\">Japonki TO 500 Bondi damskie OLAIAN</a>", "dc": 25, "sc": "Japonki, buty do wody", "or": "Nowa", "op": 39.99}, {"pr": 9.99, "sz": " ", "pp": 0.0, "sx": "U", "nm": "<a href=\"http://www.decathlon.pl/rcznik-basic-s-id_8403303.html\">R\u0119cznik Basic S 50 x 90 cm OLAIAN</a>", "dc": 33, "sc": "R\u00c4\u0099czniki", "or": "Nowa", "op": 14.99}, {"pr": 29.99, "sz": " ", "pp": 0.0, "sx": "U", "nm": "<a href=\"http://www.decathlon.pl/rcznik-basic-l-abyss-id_8486649.html\">R\u0119cznik Basic L Abyss 145 x 85 cm OLAIAN</a>", "dc": 25, "sc": "R\u00c4\u0099czniki", "or": "Nowa", "op": 39.99}, {"pr": 29.99, "sz": " ", "pp": 0.0, "sx": "U", "nm": "<a href=\"http://www.decathlon.pl/rcznik-basic-l-morea-id_8486654.html\">R\u0119cznik Basic L Morea 145 x 85 cm OLAIAN</a>", "dc": 25, "sc": "R\u00c4\u0099czniki", "or": "Nowa", "op": 39.99}, {"pr": 29.99, "sz": " ", "pp": 0.0, "sx": "U", "nm": "<a href=\"http://www.decathlon.pl/rcznik-basic-l-wave-id_8486658.html\">R\u0119cznik Basic L Wave 145 x 85 cm OLAIAN</a>", "dc": 25, "sc": "R\u00c4\u0099czniki", "or": "Nowa", "op": 39.99}, {"pr": 29.99, "sz": " ", "pp": 0.0, "sx": "U", "nm": "<a href=\"http://www.decathlon.pl/rcznik-basic-l-zao-id_8486661.html\">R\u0119cznik Basic L Zao 145 x 85 cm OLAIAN</a>", "dc": 25, "sc": "R\u00c4\u0099czniki", "or": "Nowa", "op": 39.99}, {"pr": 49.99, "sz": " M, L, 2XL, 3XL", "pp": 0.0, "sx": "M", "nm": "<a href=\"http://www.decathlon.pl/koszulka-dugi-rkaw-adv-100-id_8485165.html\">Koszulka \u017ceglarska d\u0142ugi r\u0119kaw ADVENTURE 100 m\u0119ska TRIBORD</a>", "dc": 38, "sc": "Odzie\u00c5\u00bc letnia m\u00c4\u0099ska", "or": "Nowa", "op": 79.99}, {"pr": 69.99, "sz": " 38, 40, 42, 44, 46, 52, 56", "pp": 0.0, "sx": "M", "nm": "<a href=\"http://www.decathlon.pl/koszula-100-id_8505355.html\">Koszula \u017ceglarska 100 m\u0119ska TRIBORD</a>", "dc": 30, "sc": "Odzie\u00c5\u00bc letnia m\u00c4\u0099ska", "or": "Nowa", "op": 99.99}, {"pr": 59.99, "sz": " M, L, XL, 2XL, 3XL, 4XL", "pp": 0.0, "sx": "M", "nm": "<a href=\"http://www.decathlon.pl/polo-krotki-rkaw-adv100-bloc-id_8491685.html\">Polo \u017ceglarskie kr\u00f3tki r\u0119kaw ADVENTURE 100 Bloc m\u0119skie TRIBORD</a>", "dc": 25, "sc": "Odzie\u00c5\u00bc letnia m\u00c4\u0099ska", "or": "Nowa", "op": 79.99}, {"pr": 49.99, "sz": " 2XS, L, XL, 2XL", "pp": 0.0, "sx": "F", "nm": "<a href=\"http://www.decathlon.pl/szorty-adventure-100-id_8501287.html\">Szorty \u017ceglarskie ADVENTURE 100 damskie TRIBORD</a>", "dc": 17, "sc": "Odzie\u00c5\u00bc letnia damska", "or": "Nowa", "op": 59.99}, {"pr": 49.99, "sz": " XS, XL", "pp": 49.99, "sx": "F", "nm": "<a href=\"http://www.decathlon.pl/krotka-pianka-kajakarska-500-id_8387611.html\">Kr\u00f3tka pianka bez r\u0119kaw\u00f3w na kajak i stand up paddle 500 neopren 2 mm damska ITIWIT</a>", "dc": 62, "sc": "Odzie\u00c5\u00bc na SUP", "or": "Powr\u00f3t", "op": 129.99}, {"pr": 34.99, "sz": " 6 LAT", "pp": 0.0, "sx": "J", "nm": "<a href=\"http://www.decathlon.pl/spodenki-dwustronne-id_8365721.html\">Koszulka bez r\u0119kaw\u00f3w do koszyk\u00f3wki dla dzieci TARMAK</a>", "dc": 30, "sc": "Odzie\u00c5\u00bc do koszyk\u00c3\u00b3wki", "or": "Nowa", "op": 49.99}, {"pr": 34.99, "sz": " 0, 1, 2, 3", "pp": 34.99, "sx": "U", "nm": "<a href=\"http://www.decathlon.pl/nakolanniki-v500--id_8395581.html\">Nakolanniki do siatk\u00f3wki V500 KIPSTA</a>", "dc": 13, "sc": "Siatk\u00c3\u00b3wka pla\u00c5\u00bcowa", "or": "Powr\u00f3t", "op": 39.99}, {"pr": 54.99, "sz": " ", "pp": 0.0, "sx": "U", "nm": "<a href=\"http://www.decathlon.pl/hantel-10-kg-id_1042451.html\">Zestaw hantli 10 kg DOMYOS</a>", "dc": 8, "sc": "Sprz\u00c4\u0099t  Bodybuilding", "or": "Nowa", "op": 59.99}, {"pr": 44.99, "sz": " 2XS / W26 L31, XS / W28 L31, S / W30 L31, M / W33 L31, L / W35 L31, XL / W38 L31", "pp": 0.0, "sx": "F", "nm": "<a href=\"http://www.decathlon.pl/legginsy-500-czarne-id_8484503.html\">Legginsy trening crossowy 500 damskie DOMYOS</a>", "dc": 36, "sc": "Odzie\u00c5\u00bc Cross Trening | Bodybuilding", "or": "Nowa", "op": 69.99}, {"pr": 49.99, "sz": " S / W30 L33, M / W32 L33, L / W34 L34, XL / W37 L34", "pp": 0.0, "sx": "M", "nm": "<a href=\"http://www.decathlon.pl/legginsy-500-z-nadrukiem-id_8484505.html\">Legginsy trening si\u0142owy 500 m\u0119skie DOMYOS</a>", "dc": 29, "sc": "Odzie\u00c5\u00bc Cross Trening | Bodybuilding", "or": "Nowa", "op": 69.99}, {"pr": 29.99, "sz": " S, M, L, XL, 2XL", "pp": 0.0, "sx": "M", "nm": "<a href=\"http://www.decathlon.pl/koszulka-500-id_8484536.html\">Koszulka trening crossowy 500 m\u0119ska DOMYOS</a>", "dc": 25, "sc": "Odzie\u00c5\u00bc Cross Trening | Bodybuilding", "or": "Nowa", "op": 39.99}, {"pr": 34.99, "sz": " 5 ANS, 6 LAT, 8 LAT, 10 LAT, 12 LAT, 14 LAT", "pp": 0.0, "sx": "J", "nm": "<a href=\"http://www.decathlon.pl/bluza-500-gym-id_8394417.html\">Bluza na zamek z kapturem Gym & Pilates 500 dla dzieci DOMYOS</a>", "dc": 30, "sc": "Odzie\u00c5\u00bc do Pilatesu i Gimnastyki", "or": "Nowa", "op": 49.99}, {"pr": 34.99, "sz": " 5 ANS, 6 LAT, 8 LAT, 10 LAT, 12 LAT, 14 LAT", "pp": 0.0, "sx": "J", "nm": "<a href=\"http://www.decathlon.pl/spodnie-520-slim-id_8394428.html\">Spodnie dresowe Slim Gym & Pilates 520 dla dzieci DOMYOS</a>", "dc": 30, "sc": "Odzie\u00c5\u00bc do Pilatesu i Gimnastyki", "or": "Nowa", "op": 49.99}, {"pr": 14.99, "sz": " 5 ANS, 6 LAT, 8 LAT, 10 LAT, 12 LAT, 14 LAT", "pp": 0.0, "sx": "J", "nm": "<a href=\"http://www.decathlon.pl/koszulka-500-gym-id_8489456.html\">Koszulka bez r\u0119kaw\u00f3w Gym & Pilates 500 dla dzieci DOMYOS</a>", "dc": 25, "sc": "Odzie\u00c5\u00bc do Pilatesu i Gimnastyki", "or": "Nowa", "op": 19.99}, {"pr": 14.99, "sz": " XS, M, L, XL, 2XL, 3XL", "pp": 0.0, "sx": "F", "nm": "<a href=\"http://www.decathlon.pl/koszulka-500-id_8490966.html\">Koszulka kr\u00f3tki r\u0119kaw Regular Gym & Pilates 500 damska DOMYOS</a>", "dc": 25, "sc": "Odzie\u00c5\u00bc do Pilatesu i Gimnastyki", "or": "Nowa", "op": 19.99}, {"pr": 89.99, "sz": " 6 LAT", "pp": 97.0, "sx": "J", "nm": "<a href=\"http://www.decathlon.pl/dres-fitness-adidas-id_8406477.html\">Dres fitness dla dzieci ADIDAS</a>", "dc": 47, "sc": "Odzie\u00c5\u00bc do Pilatesu i Gimnastyki", "or": "Ni\u017csza cena z 97.0", "op": 169.99}, {"pr": 19.99, "sz": " 2XS / W26 L31, XS / W28 L31, S / W30 L31", "pp": 19.99, "sx": "F", "nm": "<a href=\"http://www.decathlon.pl/rybaczki-slim-fit500-id_8367331.html\">Rybaczki Slim Gym & Pilates FIT+ 500 damskie DOMYOS</a>", "dc": 33, "sc": "Odzie\u00c5\u00bc do Pilatesu i Gimnastyki", "or": "Powr\u00f3t", "op": 29.99}, {"pr": 14.99, "sz": " M, L, XL, 2XL, 3XL, 4XL", "pp": 14.99, "sx": "M", "nm": "<a href=\"http://www.decathlon.pl/koszulka-500-slim-id_8490928.html\">Koszulka do gimnastyki i pilatesu 500 slim m\u0119ska DOMYOS</a>", "dc": 25, "sc": "Odzie\u00c5\u00bc do Pilatesu i Gimnastyki", "or": "Powr\u00f3t", "op": 19.99}, {"pr": 69.99, "sz": " M", "pp": 69.99, "sx": "F", "nm": "<a href=\"http://www.decathlon.pl/legginsy-puma-gym--id_8406353.html\">Legginsy Gym & Pilates damskie PUMA</a>", "dc": 18, "sc": "Odzie\u00c5\u00bc do Pilatesu i Gimnastyki", "or": "Powr\u00f3t", "op": 84.99}, {"pr": 39.99, "sz": " 6 LAT, 8 LAT, 10 LAT, 12 LAT, 14 LAT", "pp": 0.0, "sx": "J", "nm": "<a href=\"http://www.decathlon.pl/koszulka-polo-pl500-granatowa-id_8485589.html\">Koszulka polo je\u017adziecka PL500 dla dzieci FOUGANZA</a>", "dc": 20, "sc": "Wyposa\u00c5\u00bcenie je\u00c5\u00bad\u00c5\u00baca", "or": "Nowa", "op": 49.99}, {"pr": 89.99, "sz": " XS, S, L", "pp": 0.0, "sx": "J", "nm": "<a href=\"http://www.decathlon.pl/kask-jedziecki-safety-liwka-id_8392784.html\">Kask je\u017adziecki Safety  FOUGANZA</a>", "dc": 18, "sc": "Wyposa\u00c5\u00bcenie je\u00c5\u00bad\u00c5\u00baca", "or": "Nowa", "op": 109.99}, {"pr": 29.99, "sz": " 12 LAT", "pp": 29.99, "sx": "J", "nm": "<a href=\"http://www.decathlon.pl/koszulka-polo-hr-granat-id_8392647.html\">Koszulka polo je\u017adziecka HR dla dzieci FOUGANZA</a>", "dc": 57, "sc": "Wyposa\u00c5\u00bcenie je\u00c5\u00bad\u00c5\u00baca", "or": "Powr\u00f3t", "op": 69.99}, {"pr": 199.99, "sz": " L", "pp": 199.99, "sx": "U", "nm": "<a href=\"http://www.decathlon.pl/kurtka-do-owiectwa-spf100-5mm-id_8354126.html\">Kurtka do kombinezonu do \u0142owiectwa podwodnego i freedivingu SPF 100 5 mm  SUBEA</a>", "dc": 41, "sc": "Skafandry do \u00c5\u0081owiectwa Podwodnego", "or": "Powr\u00f3t", "op": 339.99}, {"pr": 39.99, "sz": " 44", "pp": 0.0, "sx": "F", "nm": "<a href=\"http://www.decathlon.pl/polar-eglarski-damski-cr100-id_8282306.html\">Polar \u017ceglarski RACE damski TRIBORD</a>", "dc": 33, "sc": "Odzie\u00c5\u00bc, obuwie \u00c5\u00bceglarskie", "or": "Nowa", "op": 59.99}, {"pr": 89.99, "sz": " XS, S, M, L, XL, 2XL", "pp": 0.0, "sx": "F", "nm": "<a href=\"http://www.decathlon.pl/sztormiak-eglarski-100-id_8382391.html\">Sztormiak \u017ceglarski 100 damski TRIBORD</a>", "dc": 25, "sc": "Odzie\u00c5\u00bc, obuwie \u00c5\u00bceglarskie", "or": "Nowa", "op": 119.99}, {"pr": 189.99, "sz": " S, M, L, XL, 2XL, 3XL", "pp": 0.0, "sx": "M", "nm": "<a href=\"http://www.decathlon.pl/sztormiak-eglarski-500-id_8357798.html\">Sztormiak \u017ceglarski 500 m\u0119ski TRIBORD</a>", "dc": 24, "sc": "Odzie\u00c5\u00bc, obuwie \u00c5\u00bceglarskie", "or": "Nowa", "op": 249.99}, {"pr": 139.99, "sz": " S, M, XL, 2XL, 3XL", "pp": 0.0, "sx": "M", "nm": "<a href=\"http://www.decathlon.pl/kurtka-eglarska-100-id_8383555.html\">Kurtka \u017ceglarska 100 m\u0119ska TRIBORD</a>", "dc": 22, "sc": "Odzie\u00c5\u00bc, obuwie \u00c5\u00bceglarskie", "or": "Nowa", "op": 179.99}, {"pr": 99.99, "sz": " 4 lat, 6 lat, 8 lat", "pp": 0.0, "sx": "J", "nm": "<a href=\"http://www.decathlon.pl/kurtka-eglarska-100-jr-id_8330359.html\">Kurtka \u017ceglarska 100 dla dzieci TRIBORD</a>", "dc": 17, "sc": "Odzie\u00c5\u00bc, obuwie \u00c5\u00bceglarskie", "or": "Nowa", "op": 119.99}, {"pr": 99.99, "sz": " S, M, L, XL, 2XL, 3XL", "pp": 0.0, "sx": "M", "nm": "<a href=\"http://www.decathlon.pl/sztormiak-eglarski-100-id_8388628.html\">Sztormiak \u017ceglarski 100 m\u0119ski TRIBORD</a>", "dc": 17, "sc": "Odzie\u00c5\u00bc, obuwie \u00c5\u00bceglarskie", "or": "Nowa", "op": 119.99}, {"pr": 59.99, "sz": " M, L, XL", "pp": 0.0, "sx": "M", "nm": "<a href=\"http://www.decathlon.pl/spodnie-wierzchnie-100-id_8330268.html\">\u017beglarskie spodnie wierzchnie 100 m\u0119skie TRIBORD</a>", "dc": 14, "sc": "Odzie\u00c5\u00bc, obuwie \u00c5\u00bceglarskie", "or": "Nowa", "op": 69.99}, {"pr": 59.99, "sz": " S, M, L, XL, 2XL, 3XL", "pp": 0.0, "sx": "M", "nm": "<a href=\"http://www.decathlon.pl/kurtka-essential-m-niebies-lekka-id_8330274.html\">Sztormiak \u017ceglarski Essential m\u0119ski TRIBORD</a>", "dc": 14, "sc": "Odzie\u00c5\u00bc, obuwie \u00c5\u00bceglarskie", "or": "Nowa", "op": 69.99}, {"pr": 49.99, "sz": " S, M, L, XL, 2XL, 3XL", "pp": 0.0, "sx": "M", "nm": "<a href=\"http://www.decathlon.pl/sweter-eglarski-cruise-id_8395969.html\">Sweter \u017ceglarski CRUISE m\u0119ski TRIBORD</a>", "dc": 38, "sc": "Polary, softshelle, swetry", "or": "Nowa", "op": 79.99}, {"pr": 69.99, "sz": " ", "pp": 0.0, "sx": "U", "nm": "<a href=\"http://www.decathlon.pl/okulary-eglarskie-500-pola-id_8485729.html\">Okulary przeciws\u0142oneczne do sport\u00f3w wodnych 500 wyporne, z polaryzacj\u0105, kat. 3 TRIBORD</a>", "dc": 30, "sc": "Okulary \u00c5\u00bceglarskie", "or": "Nowa", "op": 99.99}, {"pr": 4.99, "sz": " 43/46", "pp": 0.0, "sx": "U", "nm": "<a href=\"http://www.decathlon.pl/skarpety-rs100-x3-biae-id_8321138.html\">Skarpety sportowe RS100 3 pary ARTENGO</a>", "dc": 38, "sc": "Odzie\u00c5\u00bc do sport\u00c3\u00b3w rakietowych", "or": "Nowa", "op": 7.99}, {"pr": 11.99, "sz": " JUNIOR", "pp": 11.99, "sx": "U", "nm": "<a href=\"http://www.decathlon.pl/czapka-z-daszkiem-jr-roowa-id_8383561.html\">Czapka Z Daszkiem Jr R\u00f3\u017cowa Artengo</a>", "dc": 40, "sc": "Odzie\u00c5\u00bc do sport\u00c3\u00b3w rakietowych", "or": "Powr\u00f3t", "op": 19.99}, {"pr": 24.99, "sz": " 43/46", "pp": 24.99, "sx": "U", "nm": "<a href=\"http://www.decathlon.pl/skarpety-adidas-adiankle-mid-x3-2013-id_8237771.html\">Skarpetki tenisowe Adidas AdiAncle 3 pary ADIDAS</a>", "dc": 38, "sc": "Odzie\u00c5\u00bc do sport\u00c3\u00b3w rakietowych", "or": "Powr\u00f3t", "op": 39.99}, {"pr": 39.99, "sz": " L", "pp": 39.99, "sx": "M", "nm": "<a href=\"http://www.decathlon.pl/spodenki-dry-m-590-fiol-ro-id_8361673.html\">Spodenki tenis BADMINTON DRY 590 m\u0119skie ARTENGO</a>", "dc": 33, "sc": "Odzie\u00c5\u00bc do sport\u00c3\u00b3w rakietowych", "or": "Powr\u00f3t", "op": 59.99}, {"pr": 51.0, "sz": " 38", "pp": 55.0, "sx": "J", "nm": "<a href=\"http://www.decathlon.pl/buty-ts760-jr-ote-id_8351633.html\">Buty tenis TS760 dla dzieci sznurowane ARTENGO</a>", "dc": 27, "sc": "Buty do tenisa", "or": "Ni\u017csza cena z 55.0", "op": 69.99}, {"pr": 69.99, "sz": " ", "pp": 79.99, "sx": "U", "nm": "<a href=\"http://www.decathlon.pl/lotki-nr-4-x12-id_8354313.html\">Lotki do badmintona nr 4 (12 sztuk) BABOLAT VS</a>", "dc": 18, "sc": "Sprz\u00c4\u0099t do badmintona", "or": "Ni\u017csza cena z 79.99", "op": 84.99}, {"pr": 19.99, "sz": " XS, S, M, L, XL, 2XL", "pp": 0.0, "sx": "F", "nm": "<a href=\"http://www.decathlon.pl/koszulka-bezszwowa-yoga-id_8402736.html\">Top Yoga+ damski DOMYOS</a>", "dc": 50, "sc": "Odzie\u00c5\u00bc damska do jogi", "or": "Nowa", "op": 39.99}, {"pr": 69.99, "sz": " 2XS / W26 L28, XS / W28 L31, S / W30 L31, M / W33 L31, L / W35 L31, XL / W38 L31", "pp": 0.0, "sx": "F", "nm": "<a href=\"http://www.decathlon.pl/legginsy-yoga-id_8491802.html\">Legginsy do jogi Yoga+ damskie DOMYOS</a>", "dc": 30, "sc": "Odzie\u00c5\u00bc damska do jogi", "or": "Nowa", "op": 99.99}, {"pr": 59.99, "sz": " 2XS / W26 L28, S / W30 L31, M / W33 L31", "pp": 59.99, "sx": "F", "nm": "<a href=\"http://www.decathlon.pl/rybaczki-yoga-id_8491796.html\">Rybaczki do jogi Yoga damskie DOMYOS</a>", "dc": 29, "sc": "Odzie\u00c5\u00bc damska do jogi", "or": "Powr\u00f3t", "op": 84.99}, {"pr": 199.99, "sz": " ", "pp": 249.99, "sx": "U", "nm": "<a href=\"http://www.decathlon.pl/zestaw-axion-sw-240-xxh-50-80g-id_8297113.html\">Zestaw spinningowy Axion SW 240 XXH 50-80 g CAPERLAN</a>", "dc": 41, "sc": "W\u00c4\u0099dki, ko\u00c5\u0082owrotki, zestawy", "or": "Ni\u017csza cena z 249.99", "op": 339.99}, {"pr": 69.99, "sz": " ", "pp": 69.99, "sx": "U", "nm": "<a href=\"http://www.decathlon.pl/zestaw-lure-essentiel-270-id_8237125.html\">Zestaw spinningowy Lure Essentiel 270 CAPERLAN</a>", "dc": 30, "sc": "W\u00c4\u0099dki, ko\u00c5\u0082owrotki, zestawy", "or": "Powr\u00f3t", "op": 99.99}, {"pr": 4.99, "sz": " ", "pp": 0.0, "sx": "U", "nm": "<a href=\"http://www.decathlon.pl/iga-do-robakow-nierdzewna-x-2-id_8130250.html\">Ig\u0142a do robak\u00f3w nierdzewna x 2 AUTAIN PECHE</a>", "dc": 38, "sc": "Wyposa\u00c5\u00bcenie w\u00c4\u0099dkarza", "or": "Nowa", "op": 7.99}, {"pr": 4.99, "sz": " 8, 12, 14", "pp": 5.99, "sx": "U", "nm": "<a href=\"http://www.decathlon.pl/haczyki-big-bait-id_8349366.html\">Haczyki big bait CAPERLAN</a>", "dc": 44, "sc": "Przyn\u00c4\u0099ty, zan\u00c4\u0099ty, akcesoria", "or": "Ni\u017csza cena z 5.99", "op": 8.99}, {"pr": 269.99, "sz": " ", "pp": 299.99, "sx": "U", "nm": "<a href=\"http://www.decathlon.pl/wixom-200-mh-7-21-g-id_8293015.html\">W\u0119dka spinningowa Wixom 200 MH 7 - 21 g CAPERLAN</a>", "dc": 46, "sc": "W\u00c4\u0099dki spinningowe", "or": "Powr\u00f3t z ni\u017csz\u0105 cen\u0105 z 299.99", "op": 499.99}, {"pr": 19.99, "sz": " ", "pp": 19.99, "sx": "U", "nm": "<a href=\"http://www.decathlon.pl/kominiarka-actikam-furtiv-id_8368577.html\">Kominiarka ACTIKAM FURTIV SOLOGNAC</a>", "dc": 50, "sc": "Odzie\u00c5\u00bc my\u00c5\u009bliwska", "or": "Powr\u00f3t", "op": 39.99}, {"pr": 89.99, "sz": " 44, 46", "pp": 89.99, "sx": "U", "nm": "<a href=\"http://www.decathlon.pl/spodnie-myliwskie-impertane-id_8342841.html\">Spodnie my\u015bliwskie Impertane</a>", "dc": 31, "sc": "Odzie\u00c5\u00bc my\u00c5\u009bliwska", "or": "Powr\u00f3t", "op": 129.99}, {"pr": 39.99, "sz": " ", "pp": 39.99, "sx": "U", "nm": "<a href=\"http://www.decathlon.pl/wabik-kaczki-krzyowki-id_8399904.html\">Wabik kaczki krzy\u017c\u00f3wki RIVOLIER</a>", "dc": 33, "sc": "Akcesoria my\u00c5\u009bliwskie", "or": "Powr\u00f3t", "op": 59.99}, {"pr": 74.99, "sz": " 38, 39, 42", "pp": 0.0, "sx": "M", "nm": "<a href=\"http://www.decathlon.pl/buty-soft-520-id_8352604.html\">Buty do szybkiego marszu Soft 520 damskie NEWFEEL</a>", "dc": 38, "sc": "Obuwie do aktywnego marszu", "or": "Nowa", "op": 119.99}, {"pr": 64.99, "sz": " 39, 40", "pp": 64.99, "sx": "M", "nm": "<a href=\"http://www.decathlon.pl/buty-propulse-walk-240-id_8366314.html\">Buty do szybkiego marszu Propulse Walk 240 m\u0119skie NEWFEEL</a>", "dc": 50, "sc": "Obuwie do aktywnego marszu", "or": "Powr\u00f3t", "op": 129.99}, {"pr": 89.99, "sz": " ", "pp": 0.0, "sx": "U", "nm": "<a href=\"http://www.decathlon.pl/kijki-propulse-walk-120-czarne-id_8364297.html\">Kijki do nordic walking Propulse Walk 120 NEWFEEL</a>", "dc": 31, "sc": "Nordic walking", "or": "Nowa", "op": 129.99}, {"pr": 124.99, "sz": " 105 CM, 110 CM, 115 CM, 120 CM, 125 CM", "pp": 100.0, "sx": "U", "nm": "<a href=\"http://www.decathlon.pl/kijki-pw-p500-czerwone-id_8354018.html\">Kijki do nordic walking PW P500 czerwone / czarne NEWFEEL</a>", "dc": 26, "sc": "Nordic walking", "or": "Powr\u00f3t z wy\u017csz\u0105 cen\u0105 z 100.0", "op": 169.99}, {"pr": 19.99, "sz": " ", "pp": 0.0, "sx": "U", "nm": "<a href=\"http://www.decathlon.pl/zestaw-5-pior-do-lotek--id_8324022.html\">Zestaw 5 Pi\u00f3r Do Lotek Geologic</a>", "dc": 20, "sc": "Akcesoria do darta", "or": "Nowa", "op": 24.99}, {"pr": 19.99, "sz": " 4 LATA, 6 LAT, 8 LAT, 10 LAT, 12 LAT, 14 LAT", "pp": 0.0, "sx": "J", "nm": "<a href=\"http://www.decathlon.pl/top-uv-500-jr-id_8403257.html\">TOP UV termiczny surfing kr\u00f3tki r\u0119kaw 500 dla dzieci OLAIAN</a>", "dc": 33, "sc": "Pianki, akcesoria windsurfngowe", "or": "Nowa", "op": 29.99}, {"pr": 29.99, "sz": " 36, 44", "pp": 29.99, "sx": "F", "nm": "<a href=\"http://www.decathlon.pl/koszulka-bez-rkawow-id_8490337.html\">Koszulka bez r\u0119kaw\u00f3w do ta\u0144ca damska DOMYOS</a>", "dc": 40, "sc": "Taniec nowoczesny, street dance", "or": "Powr\u00f3t", "op": 49.99}, {"pr": 9.99, "sz": " ", "pp": 9.99, "sx": "U", "nm": "<a href=\"http://www.decathlon.pl/gumka-do-wosow-id_8394245.html\">Gumka do gimnastyki  DOMYOS</a>", "dc": 33, "sc": "Gimnastyka Artystyczna i Rytmiczna", "or": "Powr\u00f3t", "op": 14.99}, {"pr": 84.99, "sz": " 6 OZ, 8 OZ", "pp": 0.0, "sx": "U", "nm": "<a href=\"http://www.decathlon.pl/rkawice-bokserskie-ergo-foam-id_8191112.html\">R\u0119kawice bokserskie ERGO FOAM EVERLAST</a>", "dc": 35, "sc": "R\u00c4\u0099kawice bokserskie, chwytne, banda\u00c5\u00bce, owijki", "or": "Nowa", "op": 129.99}, {"pr": 329.99, "sz": " ", "pp": 0.0, "sx": "U", "nm": "<a href=\"http://www.decathlon.pl/stojak-na-worek-treningowy-id_8099632.html\">Stojak na worek treningowy DOMYOS</a>", "dc": 17, "sc": "Worki bokserskie, tarcze trenera", "or": "Nowa", "op": 399.0}, {"pr": 69.99, "sz": " XS", "pp": 69.99, "sx": "M", "nm": "<a href=\"http://www.decathlon.pl/koszulka-bez-rkawow-id_8367919.html\">Koszulka bokserska bez r\u0119kaw\u00f3w na zamek OUTSHOCK</a>", "dc": 36, "sc": "Buty, Odzie\u00c5\u00bc bokserska", "or": "Powr\u00f3t", "op": 109.99}, {"pr": 29.99, "sz": " ", "pp": 0.0, "sx": "U", "nm": "<a href=\"http://www.decathlon.pl/parasol-do-golfa-120-uv-be-id_8390880.html\">Parasol do golfa 120 UV INESIS</a>", "dc": 33, "sc": "Pi\u00c5\u0082ki golfowe i akcesoria", "or": "Nowa", "op": 44.99}, {"pr": 34.99, "sz": " ", "pp": 34.99, "sx": "J", "nm": "<a href=\"http://www.decathlon.pl/czapka-z-daszkiem-roowa-id_8386663.html\">Czapka z daszkiem do golfa TITLEIST</a>", "dc": 42, "sc": "Pi\u00c5\u0082ki golfowe i akcesoria", "or": "Powr\u00f3t", "op": 59.99}, {"pr": 39.99, "sz": " S, 2XL, 3XL", "pp": 0.0, "sx": "M", "nm": "<a href=\"http://www.decathlon.pl/spodenki-bermudy-500-niebieski-id_8489494.html\">Spodenki do golfa bermudy 500 m\u0119skie INESIS</a>", "dc": 20, "sc": "Odzie\u00c5\u00bc i obuwie do golfa", "or": "Nowa", "op": 49.99}, {"pr": 39.99, "sz": " 2XS, M, L, XL", "pp": 0.0, "sx": "F", "nm": "<a href=\"http://www.decathlon.pl/spodenki-do-golfa-500-niebiesk-id_8489504.html\">Spodenki do golfa 500 damskie INESIS</a>", "dc": 20, "sc": "Odzie\u00c5\u00bc i obuwie do golfa", "or": "Nowa", "op": 49.99}, {"pr": 49.99, "sz": " 40, 42, 44, 46, 48, 50", "pp": 49.99, "sx": "M", "nm": "<a href=\"http://www.decathlon.pl/spodenki-bermudy-900-czerwone-id_8489506.html\">Spodenki do golfa bermudy 900 m\u0119skie INESIS</a>", "dc": 38, "sc": "Odzie\u00c5\u00bc i obuwie do golfa", "or": "Powr\u00f3t", "op": 79.99}, {"pr": 303.0, "sz": " 8 LAT, 12 LAT", "pp": 304.0, "sx": "J", "nm": "<a href=\"http://www.decathlon.pl/kurtka-900-id_8397873.html\">Kurtka narciarska 900 dla dzieci WED'ZE</a>", "dc": 20, "sc": "Odzie\u00c5\u00bc narciarska", "or": "Ni\u017csza cena z 304.0", "op": 379.99}, {"pr": 99.99, "sz": " 12 MIESIACE", "pp": 99.99, "sx": "M", "nm": "<a href=\"http://www.decathlon.pl/kombinezon-na-sanki-100-id_8371536.html\">Kombinezon na sanki 100 WED'ZE</a>", "dc": 23, "sc": "Odzie\u00c5\u00bc narciarska", "or": "Powr\u00f3t", "op": 129.99}, {"pr": 39.99, "sz": " M, L", "pp": 39.99, "sx": "U", "nm": "<a href=\"http://www.decathlon.pl/rkawice-narciarskie-slide-300-id_8371093.html\">R\u0119kawice narciarskie jednopalczaste SLIDE 300 WED'ZE</a>", "dc": 33, "sc": "R\u00c4\u0099kawice narciarskie", "or": "Powr\u00f3t", "op": 59.99}, {"pr": 156.0, "sz": " 110 CM, 120 CM, 130 CM, 140 CM, 150 CM, 160 CM", "pp": 157.0, "sx": "J", "nm": "<a href=\"http://www.decathlon.pl/narty-classic-20-nnn-id_8401595.html\">Narty biegowe Classic 20 NNN dla dzieci QUECHUA</a>", "dc": 8, "sc": "Sprz\u00c4\u0099t i odzie\u00c5\u00bc juniorski", "or": "Ni\u017csza cena z 157.0", "op": 169.99}, {"pr": 14.99, "pp": 44.99, "sx": "U", "nm": "<a href=\"http://www.decathlon.pl/koszulka-ff100-brazylia-id_8406957.html\">Koszulka kr\u00f3tki r\u0119kaw do pi\u0142ki no\u017cnej FF100 Brazylia dla dzieci KIPSTA</a>", "dc": 66, "sc": "Pi\u00c5\u0082karski Sklep Kibica", "rl": "/koszulka-ff100-brazylia-id_8406957.html", "or": "Obni\u017cka", "op": 44.99}, {"pr": 14.99, "pp": 44.99, "sx": "U", "nm": "<a href=\"http://www.decathlon.pl/t-shirt-ff100-brazylia-id_8406961.html\">T-shirt do gry w pi\u0142k\u0119 no\u017cn\u0105 FF100 Brazylia KIPSTA</a>", "dc": 66, "sc": "Pi\u00c5\u0082karski Sklep Kibica", "rl": "/t-shirt-ff100-brazylia-id_8406961.html", "or": "Obni\u017cka", "op": 44.99}, {"pr": 9.99, "pp": 24.99, "sx": "U", "nm": "<a href=\"http://www.decathlon.pl/koszulka-hike-500-dla-dzieci-id_8383245.html\">Koszulka turystyczna Hike 500 dla dziewczynek QUECHUA</a>", "dc": 60, "sc": "Koszulki do turystyki g\u00c3\u00b3rskiej", "rl": "/koszulka-hike-500-dla-dzieci-id_8383245.html", "or": "Obni\u017cka", "op": 24.99}, {"pr": 24.99, "pp": 44.99, "sx": "U", "nm": "<a href=\"http://www.decathlon.pl/koszulka-ff100-niemcy-id_8406917.html\">Koszulka kr\u00f3tki r\u0119kaw do pi\u0142ki no\u017cnej FF100 Niemcy KIPSTA</a>", "dc": 44, "sc": "Pi\u00c5\u0082karski Sklep Kibica", "rl": "/koszulka-ff100-niemcy-id_8406917.html", "or": "Obni\u017cka", "op": 44.99}, {"pr": 24.99, "pp": 44.99, "sx": "U", "nm": "<a href=\"http://www.decathlon.pl/t-shirt-ff100-jr-argentyna-id_8406969.html\">T-shirt do pi\u0142ki no\u017cnej FF100 Argentyna dla dzieci  KIPSTA</a>", "dc": 44, "sc": "Pi\u00c5\u0082karski Sklep Kibica", "rl": "/t-shirt-ff100-jr-argentyna-id_8406969.html", "or": "Obni\u017cka", "op": 44.99}, {"pr": 8.49, "pp": 14.99, "sx": "U", "nm": "<a href=\"http://www.decathlon.pl/miarka-do-gry-w-bule-id_8388721.html\">Miarka do gry w bule GEOLOGIC</a>", "dc": 43, "sc": "Akcesoria do buli", "rl": "/miarka-do-gry-w-bule-id_8388721.html", "or": "Obni\u017cka", "op": 14.99}, {"pr": 699.99, "pp": 1219.0, "sx": "U", "nm": "<a href=\"http://www.decathlon.pl/zegarek-vivoactive-hr-id_8375479.html\">Zegarek Sportowy Gps Vivoactive Hr Garmin</a>", "dc": 42, "sc": "Zegarki do biegania, pulsometry, GPS", "rl": "/zegarek-vivoactive-hr-id_8375479.html", "or": "Obni\u017cka", "op": 1219.0}, {"pr": 19.99, "pp": 34.99, "sx": "U", "nm": "<a href=\"http://www.decathlon.pl/suchawki-onear-50-id_8347910.html\">S\u0142uchawki sportowe ONear 50 GEONAUTE</a>", "dc": 42, "sc": "Akcesoria do joggingu", "rl": "/suchawki-onear-50-id_8347910.html", "or": "Obni\u017cka", "op": 34.99}, {"pr": 219.99, "pp": 369.99, "sx": "U", "nm": "<a href=\"http://www.decathlon.pl/koszulka-brazylia-id_8480017.html\">Koszulka kr\u00f3tki r\u0119kaw do pi\u0142ki no\u017cnej Brazylia NIKE</a>", "dc": 40, "sc": "Pi\u00c5\u0082karski Sklep Kibica", "rl": "/koszulka-brazylia-id_8480017.html", "or": "Obni\u017cka", "op": 369.99}, {"pr": 14.99, "pp": 24.99, "sx": "U", "nm": "<a href=\"http://www.decathlon.pl/pasta-montaowa-do-karbonu-id_8402877.html\">Pasta Monta\u017cowa Do Karbonu B'Twin</a>", "dc": 40, "sc": "Cz\u00c4\u0099\u00c5\u009bci rowerowe", "rl": "/pasta-montaowa-do-karbonu-id_8402877.html", "or": "Obni\u017cka", "op": 24.99}, {"pr": 14.99, "pp": 24.99, "sx": "U", "nm": "<a href=\"http://www.decathlon.pl/spodenki-500-id_8489393.html\">Spodenki do gimnastyki 500 dla dzieci DOMYOS</a>", "dc": 40, "sc": "Odzie\u00c5\u00bc do Pilatesu i Gimnastyki", "rl": "/spodenki-500-id_8489393.html", "or": "Obni\u017cka", "op": 24.99}, {"pr": 189.99, "pp": 309.99, "sx": "U", "nm": "<a href=\"http://www.decathlon.pl/koszulka-brazylia-id_8480018.html\">Koszulka kr\u00f3tki r\u0119kaw do pi\u0142ki no\u017cnej Brazylia dla dzieci NIKE</a>", "dc": 38, "sc": "Pi\u00c5\u0082karski Sklep Kibica", "rl": "/koszulka-brazylia-id_8480018.html", "or": "Obni\u017cka", "op": 309.99}, {"pr": 199.99, "pp": 299.99, "sx": "U", "nm": "<a href=\"http://www.decathlon.pl/kurtka-mh500-wtp-damska-id_8492362.html\">Kurtka turystyczna MH500 WTP damska QUECHUA</a>", "dc": 33, "sc": "Turystyka g\u00c3\u00b3rska", "rl": "/kurtka-mh500-wtp-damska-id_8492362.html", "or": "Obni\u017cka", "op": 299.99}, {"pr": 199.99, "pp": 299.99, "sx": "U", "nm": "<a href=\"http://www.decathlon.pl/kurtka-mh-500-wtp-mska-id_8492418.html\">Kurtka turystyczna MH500 WTP m\u0119ska QUECHUA</a>", "dc": 33, "sc": "Turystyka g\u00c3\u00b3rska", "rl": "/kurtka-mh-500-wtp-mska-id_8492418.html", "or": "Obni\u017cka", "op": 299.99}, {"pr": 99.99, "pp": 149.99, "sx": "U", "nm": "<a href=\"http://www.decathlon.pl/kurtka-polarowa-fh500-mska-id_8492307.html\">Kurtka polarowa FH500 Helium m\u0119ska QUECHUA</a>", "dc": 33, "sc": "Szybkie w\u00c4\u0099dr\u00c3\u00b3wki po g\u00c3\u00b3rach", "rl": "/kurtka-polarowa-fh500-mska-id_8492307.html", "or": "Obni\u017cka", "op": 149.99}, {"pr": 19.99, "pp": 29.99, "sx": "U", "nm": "<a href=\"http://www.decathlon.pl/saszetka-na-smartfon-id_8297581.html\">Pas na smartfon do biegania KALENJI</a>", "dc": 33, "sc": "Akcesoria do biegania", "rl": "/saszetka-na-smartfon-id_8297581.html", "or": "Obni\u017cka", "op": 29.99}, {"pr": 9.99, "pp": 14.99, "sx": "U", "nm": "<a href=\"http://www.decathlon.pl/sznurowada-okrge-id_8307992.html\">Sznurowad\u0142a turystyczne okr\u0105g\u0142e QUECHUA</a>", "dc": 33, "sc": "Akcesoria turystyczne", "rl": "/sznurowada-okrge-id_8307992.html", "or": "Obni\u017cka", "op": 14.99}, {"pr": 9.99, "pp": 14.99, "sx": "U", "nm": "<a href=\"http://www.decathlon.pl/rcznik-do-rk-id_8342761.html\">R\u0119cznik do r\u0105k CAPERLAN</a>", "dc": 33, "sc": "Wyposa\u00c5\u00bcenie w\u00c4\u0099dkarza", "rl": "/rcznik-do-rk-id_8342761.html", "or": "Obni\u017cka", "op": 14.99}, {"pr": 24.99, "pp": 34.99, "sx": "U", "nm": "<a href=\"http://www.decathlon.pl/wiadro-zantowe-18-l-id_3343575.html\">Wiadro zan\u0119towe przezroczyste 18 l CAPERLAN</a>", "dc": 28, "sc": "Wyposa\u00c5\u00bcenie w\u00c4\u0099dkarza", "rl": "/wiadro-zantowe-18-l-id_3343575.html", "or": "Obni\u017cka", "op": 34.99}, {"pr": 279.99, "pp": 379.99, "sx": "U", "nm": "<a href=\"http://www.decathlon.pl/koszulka-argentyna-2018-id_8408147.html\">Koszulka do pi\u0142ki no\u017cnej kr\u00f3tki r\u0119kaw Argentyna 2018 ADIDAS</a>", "dc": 26, "sc": "Pi\u00c5\u0082karski Sklep Kibica", "rl": "/koszulka-argentyna-2018-id_8408147.html", "or": "Obni\u017cka", "op": 379.99}, {"pr": 219.99, "pp": 299.99, "sx": "U", "nm": "<a href=\"http://www.decathlon.pl/koszulka-argentyna-replika-id_8408148.html\">Koszulka do pi\u0142ki no\u017cnej kr\u00f3tki r\u0119kaw Argentyna 2018 dla dzieci ADIDAS</a>", "dc": 26, "sc": "Pi\u00c5\u0082karski Sklep Kibica", "rl": "/koszulka-argentyna-replika-id_8408148.html", "or": "Obni\u017cka", "op": 299.99}, {"pr": 14.99, "pp": 19.99, "sx": "U", "nm": "<a href=\"http://www.decathlon.pl/pasta-kukurydziano-waniliowa-id_8351772.html\">Pasta kukurydziano-waniliowa 200 gram DYNAMITE BAITS</a>", "dc": 25, "sc": "Przyn\u00c4\u0099ty, zan\u00c4\u0099ty, akcesoria", "rl": "/pasta-kukurydziano-waniliowa-id_8351772.html", "or": "Obni\u017cka", "op": 19.99}, {"pr": 279.99, "pp": 369.99, "sx": "U", "nm": "<a href=\"http://www.decathlon.pl/buty-merrell-maipo-mskie-id_8359798.html\">Buty turystyczne niskie Merrell Maipo m\u0119skie MERRELL</a>", "dc": 24, "sc": "Turystyka krajoznawcza", "rl": "/buty-merrell-maipo-mskie-id_8359798.html", "or": "Obni\u017cka", "op": 369.99}, {"pr": 199.99, "pp": 259.95, "sx": "U", "nm": "<a href=\"http://www.decathlon.pl/wdka-pole-carbon-950-id_8014344.html\">W\u0119dka Pole carbon 950 CAPERLAN</a>", "dc": 23, "sc": "W\u00c4\u0099dki, ko\u00c5\u0082owrotki, zestawy", "rl": "/wdka-pole-carbon-950-id_8014344.html", "or": "Obni\u017cka", "op": 259.95}, {"pr": 49.99, "pp": 64.99, "sx": "U", "nm": "<a href=\"http://www.decathlon.pl/owijki-biae-x4-id_8312008.html\">Owijki dla konia i kuca 3 m x4 FOUGANZA</a>", "dc": 23, "sc": "Wyposa\u00c5\u00bcenie je\u00c5\u00bad\u00c5\u00baca", "rl": "/owijki-biae-x4-id_8312008.html", "or": "Obni\u017cka", "op": 64.99}, {"pr": 39.99, "pp": 49.99, "sx": "U", "nm": "<a href=\"http://www.decathlon.pl/koszulka-mh520-mska-id_8492284.html\">Koszulka turystyczna kr\u00f3tki r\u0119kaw MH520 m\u0119ska QUECHUA</a>", "dc": 20, "sc": "Turystyka g\u00c3\u00b3rska", "rl": "/koszulka-mh520-mska-id_8492284.html", "or": "Obni\u017cka", "op": 49.99}, {"pr": 19.99, "pp": 24.99, "sx": "U", "nm": "<a href=\"http://www.decathlon.pl/pianka-pva-fox-id_5619945.html\">Pianka PVA FOX FOX</a>", "dc": 20, "sc": "W\u00c4\u0099dkarstwo karpiowe", "rl": "/pianka-pva-fox-id_5619945.html", "or": "Obni\u017cka", "op": 24.99}, {"pr": 19.99, "pp": 24.99, "sx": "U", "nm": "<a href=\"http://www.decathlon.pl/wiadro-zantowe-mae-12-l-id_8096672.html\">Wiadro zan\u0119towe ma\u0142e (12 l) CAPERLAN</a>", "dc": 20, "sc": "Wyposa\u00c5\u00bcenie w\u00c4\u0099dkarza", "rl": "/wiadro-zantowe-mae-12-l-id_8096672.html", "or": "Obni\u017cka", "op": 24.99}, {"pr": 179.99, "pp": 219.99, "sx": "U", "nm": "<a href=\"http://www.decathlon.pl/spodnie-rock-damskie-id_8495264.html\">Spodnie Rock damskie SIMOND</a>", "dc": 18, "sc": "Alpinizm", "rl": "/spodnie-rock-damskie-id_8495264.html", "or": "Obni\u017cka", "op": 219.99}, {"pr": 89.99, "pp": 109.99, "sx": "U", "nm": "<a href=\"http://www.decathlon.pl/rybaczki-wspinaczkowe-cliff-sz-id_8495274.html\">Rybaczki wspinaczkowe Cliff m\u0119skie SIMOND</a>", "dc": 18, "sc": "Wspinaczka", "rl": "/rybaczki-wspinaczkowe-cliff-sz-id_8495274.html", "or": "Obni\u017cka", "op": 109.99}, {"pr": 24.99, "pp": 29.99, "sx": "U", "nm": "<a href=\"http://www.decathlon.pl/korek-drabinka-klucz-nr-4-id_8238732.html\">Korek do amortyzatora + drabinka + klucz nr 4 SENSAS</a>", "dc": 16, "sc": "W\u00c4\u0099dki, ko\u00c5\u0082owrotki, zestawy", "rl": "/korek-drabinka-klucz-nr-4-id_8238732.html", "or": "Obni\u017cka", "op": 29.99}, {"pr": 29.99, "pp": 34.99, "sx": "U", "nm": "<a href=\"http://www.decathlon.pl/kapelusz-trek-100-light-id_8383412.html\">Kapelusz trekkingowy TREK 100 LIGHT ultra compact FORCLAZ</a>", "dc": 14, "sc": "Czapki, kapelusze turystyczne", "rl": "/kapelusz-trek-100-light-id_8383412.html", "or": "Obni\u017cka", "op": 34.99}, {"pr": 4329.0, "pp": 5019.0, "sx": "U", "nm": "<a href=\"http://www.decathlon.pl/kompletna-rama-ultra-cf-id_8500450.html\">Kompletna Rama Rowerowa Ultra Cf B'Twin</a>", "dc": 13, "sc": "Rowery", "rl": "/kompletna-rama-ultra-cf-id_8500450.html", "or": "Obni\u017cka", "op": 5019.0}, {"pr": 199.99, "pp": 229.99, "sx": "U", "nm": "<a href=\"http://www.decathlon.pl/bryczesy-br700-granatowe-id_8383352.html\">Bryczesy BR700 m\u0119skie FOUGANZA</a>", "dc": 13, "sc": "Wyposa\u00c5\u00bcenie je\u00c5\u00bad\u00c5\u00baca", "rl": "/bryczesy-br700-granatowe-id_8383352.html", "or": "Obni\u017cka", "op": 229.99}, {"pr": 6.99, "pp": 7.99, "sx": "U", "nm": "<a href=\"http://www.decathlon.pl/4-gowki-jigowe-okrge-2-g-id_8349928.html\">4 g\u0142\u00f3wki jigowe okr\u0105g\u0142e 2 g CAPERLAN</a>", "dc": 12, "sc": "Przyn\u00c4\u0099ty, zan\u00c4\u0099ty, akcesoria", "rl": "/4-gowki-jigowe-okrge-2-g-id_8349928.html", "or": "Obni\u017cka", "op": 7.99}, {"pr": 389.99, "pp": 439.99, "sx": "U", "nm": "<a href=\"http://www.decathlon.pl/rakieta-extreme-2018-id_8512682.html\">Rakieta do padla EXTREME 2018 HEAD</a>", "dc": 11, "sc": "Rakiety", "rl": "/rakieta-extreme-2018-id_8512682.html", "or": "Obni\u017cka", "op": 439.99}, {"pr": 149.99, "pp": 169.99, "sx": "U", "nm": "<a href=\"http://www.decathlon.pl/buty-mtb-st-100-id_8500653.html\">Buty Na Rower Mtb St 100 Rockrider</a>", "dc": 11, "sc": "Odzie\u00c5\u00bc rowerowa", "rl": "/buty-mtb-st-100-id_8500653.html", "or": "Obni\u017cka", "op": 169.99}, {"pr": 79.99, "pp": 89.99, "sx": "U", "nm": "<a href=\"http://www.decathlon.pl/koszulka-polo-pl500-mesh-sz-br-id_8383341.html\">Koszulka polo je\u017adziecka PL500 Mesh m\u0119ska FOUGANZA</a>", "dc": 11, "sc": "Wyposa\u00c5\u00bcenie je\u00c5\u00bad\u00c5\u00baca", "rl": "/koszulka-polo-pl500-mesh-sz-br-id_8383341.html", "or": "Obni\u017cka", "op": 89.99}, {"pr": 39.99, "pp": 44.99, "sx": "U", "nm": "<a href=\"http://www.decathlon.pl/kapelusz-trek-500-id_8355862.html\">Kapelusz trekkingowy TREK 500 anty-UV FORCLAZ</a>", "dc": 11, "sc": "Czapki, kapelusze turystyczne", "rl": "/kapelusz-trek-500-id_8355862.html", "or": "Obni\u017cka", "op": 44.99}, {"pr": 39.99, "pp": 44.99, "sx": "U", "nm": "<a href=\"http://www.decathlon.pl/skarpety-jedz-hr-500-light-id_8485840.html\">Skarpety je\u017adzieckie HR 500 Light damskie 2 pary FOUGANZA</a>", "dc": 11, "sc": "Wyposa\u00c5\u00bcenie je\u00c5\u00bad\u00c5\u00baca", "rl": "/skarpety-jedz-hr-500-light-id_8485840.html", "or": "Obni\u017cka", "op": 44.99}]