[
    {
        "dc": 33, 
        "nm": "Bezr\u0119kawnik turystyczny dla dzieci polarowy Forclaz 500", 
        "op": 44.99, 
        "or": "Powr\u00f3t", 
        "pp": "29.99", 
        "pr": 29.99, 
        "rl": "http://www.decathlon.pl/bezrkawnik-turystyczny-dla-dzieci-polarowy-forclaz-500-id_8284326.html", 
        "sz": []
    }, 
    {
        "dc": 36, 
        "nm": "Spodnie lu\u017ane szare", 
        "op": 69.99, 
        "or": "Powr\u00f3t", 
        "pp": "44.99", 
        "pr": 44.99, 
        "rl": "http://www.decathlon.pl/spodnie-lune-szare-id_8327460.html", 
        "sz": [
            "XL"
        ]
    }, 
    {
        "dc": 23, 
        "nm": "Buty Baby LK SPORT", 
        "op": 109.99, 
        "or": "Powr\u00f3t", 
        "pp": "84.99", 
        "pr": 84.99, 
        "rl": "http://www.decathlon.pl/buty-baby-lk-sport-id_8326943.html", 
        "sz": [
            "24"
        ]
    }, 
    {
        "dc": 18, 
        "nm": "BUTY do biegania damskie GALAXY ELITE ", 
        "op": 169.99, 
        "or": "Nowa", 
        "pp": "0.0", 
        "pr": 139.99, 
        "rl": "http://www.decathlon.pl/buty-do-biegania-damskie-galaxy-elite--id_8340672.html", 
        "sz": [
            "36", 
            "37", 
            "38", 
            "39", 
            "40", 
            "41", 
            "42"
        ]
    }, 
    {
        "dc": 50, 
        "nm": "Gel Stormhawk", 
        "op": 279.99, 
        "or": "Ni\u017csza cena z 149.99", 
        "pp": "149.99", 
        "pr": 139.99, 
        "rl": "http://www.decathlon.pl/gel-stormhawk-id_8339733.html", 
        "sz": [
            "37", 
            "40"
        ]
    }
]